Workbook

Sheet Assumptions
B1: FDRE Bid Financial Model — Assumptions
B2: NHPC FDRE Tranche-II · 200 MW · Rajasthan portfolio · All cells in BLUE are inputs; YELLOW cells are the solver levers.
B4: LEGEND & HOW TO USE
B5: Blue text = hardcoded input · Black = formula · Green = link to another sheet · Yellow fill = key lever.
B6: To re-derive the bid tariff after changing any assumption: Data ▸ What-If Analysis ▸ Goal Seek —
B7: set 'Financial Model'!C68 (Equity IRR) to 0.14 by changing Assumptions!C11 (Bid tariff).
B8: Then verify 'Financial Model'!C70 Min DSCR ≥ 1.10 (if it binds instead, Goal Seek on C70).
B10: A. OPTIMIZED BID CONFIGURATION (optimizer output — engine run, seed 42)
B11: Solar capacity (AC) | C11: 288.8 | D11: MW | E11: Optimizer result
B12: Wind capacity | C12: 40.9 | D12: MW | E12: Optimizer result
B13: BESS power | C13: 180 | D13: MW | E13: Optimizer result
B14: BESS energy | C14: 540 | D14: MWh | E14: Optimizer result
B15: Contracted (bid) capacity | C15: 200 | D15: MW | E15: Selected bid capacity
B16: Bid tariff (levelized) | C16: 5.9113 | D16: Rs/kWh | E16: REQUIRED TARIFF at declared-value delivery (CUF 40%, availability 90%): lowest tariff meeting IRR & DSCR targets — re-derive via Goal Seek (see legend)
B18: B. TENDER RULES (NHPC FDRE Tranche-II RfS)
B19: Declared annual CUF | C19: 0.4 | E19: RfS: bid declaration, min 40%
B20: Annual CUF lower tolerance | C20: 0.15 | E20: RfS: -15% on declared CUF
B21: Annual CUF upper multiplier | C21: 1.1 | D21: x | E21: RfS: NHPC offtake capped at +10%
B22: PPA offtake target (x declared CUF) | C22: 1 | D22: x | E22: SCENARIO LEVER: 1.00 = deliver at declared CUF (this case); 1.10 = deliver at the +10% offtake cap (gives Rs 5.58)
B23: Hours per year (CUF convention) | C23: 8766 | D23: h | E23: RfS LD illustration uses 8,766 h
B24: Peak availability floor (monthly) | C24: 0.9 | E24: RfS: 90% of contracted capacity in peak hours
B25: Peak hours per day | C25: 4 | D25: h | E25: 2 morning (05-10) + 2 evening (18-23), buyer-scheduled
B26: Liquidated damages multiplier | C26: 1.5 | D26: x tariff | E26: Applies to monthly-peak and annual-CUF shortfall
B27: PSM charge | C27: 0.02 | D27: Rs/kWh | E27: Netted from tariff in revenue
B28: PPA term | C28: 25 | D28: years
B30: C. RESOURCE & DELIVERED YIELD
B31: Solar net CUF (P50, base) | C31: 0.275 | E31: PVsyst — TOPCon bifacial, 1.5 DC/AC
B32: Wind net CUF (P50, base) | C32: 0.34 | E32: Project configuration; measured Bikaner data
B33: Measured-yield calibration factor | C33: 1.191142 | D33: x | E33: Calibrates synthetic base CUFs to the measured-trace optimizer run that produced the bid (engine seed 42). Change only with new yield studies.
B34: Delivery efficiency to POI | C34: 0.9 | E34: BESS cycling losses + spill in firming the peak blocks
B35: Solar degradation | C35: 0.005 | D35: /yr
B36: Wind degradation | C36: 0.002 | D36: /yr
B37: Merchant capture of surplus | C37: 0.6 | E37: Curtailment haircut and solar-hour price factor on surplus sales
B39: D. CAPEX UNIT RATES (Rs cr)
B40: Solar EPC | C40: 3.1 | D40: cr/MWac | E40: Project configuration
B41: Wind EPC | C41: 6.5 | D41: cr/MW
B42: BESS energy | C42: 1.1 | D42: cr/MWh
B43: BESS PCS | C43: 0.3 | D43: cr/MW
B44: Land & development — lump sum | C44: 90 | D44: cr | E44: Project configuration
B45: Land — solar | C45: 0.45 | D45: cr/MWac
B46: Land — wind | C46: 0.08 | D46: cr/MW
B47: Land — BESS | C47: 0.02 | D47: cr/MWh
B48: Transmission — lump sum | C48: 180 | D48: cr | E48: Project configuration
B49: Transmission — per MW (evacuation basis) | C49: 1 | D49: cr/MW
B50: Interconnection limit (3 nodes) | C50: 280 | D50: MW | E50: Fatehgarh 30 + Bikaner III 150 + Bikaner II 100
B51: Owner's costs — lump sum | C51: 60 | D51: cr
B52: Owner's costs — per MW (all assets) | C52: 0.12 | D52: cr/MW
B53: Success charge | C53: 1 | D53: lakh/MW +18% GST | E53: On contracted capacity
B54: Processing fee (100–250 MW slab) | C54: 10 | D54: lakh +18% GST | E54: RfS slab
B55: Contingency | C55: 0.03 | D55: of base capex
B57: E. O&M AND OTHER OPEX
B58: Solar O&M | C58: 5.5 | D58: lakh/MW/yr
B59: Wind O&M | C59: 11 | D59: lakh/MW/yr
B60: BESS O&M | C60: 1.2 | D60: lakh/MWh/yr
B61: Admin — fixed | C61: 5 | D61: cr/yr
B62: Admin — per MW (all assets) | C62: 0.75 | D62: lakh/MW/yr
B63: Transmission O&M (evacuation basis) | C63: 2 | D63: lakh/MW/yr
B64: Insurance | C64: 0.0035 | D64: of hard capex/yr
B65: O&M escalation | C65: 0.035 | D65: /yr
B66: Transmission loss | C66: 0.005 | D66: of PPA revenue
B68: F. FINANCING
B69: Debt fraction | C69: 0.75 | D69: of project cost
B70: Interest rate (long-term debt) | C70: 0.0875 | D70: /yr
B71: Debt tenor | C71: 18 | D71: years | E71: Sculpted repayment (constant DSCR)
B72: Sculpting DSCR constant | C72: 1.478214 | D72: x | E72: Sets debt service = CFADS / this constant. Re-solve by Goal Seek: Capex!G31 (closing debt yr-18) to 0 by changing this cell.
B73: Construction period | C73: 24 | D73: months
B74: Drawdown — year 1 | C74: 0.45
B75: Drawdown — year 2 | C75: 0.55
B76: Target equity IRR | C76: 0.14 | E76: Bid solve criterion
B77: Minimum DSCR floor | C77: 1.1 | D77: x | E77: Bid solve criterion
B78: Equity discount rate (NPV) | C78: 0.1
B79: Receivable days | C79: 60 | D79: days | E79: Working capital
B80: Working-capital interest rate | C80: 0.095 | D80: /yr
B82: G. TAX & DEPRECIATION
B83: Corporate tax rate (Sec 115BAA) | C83: 0.25168 | E83: Incl. surcharge & cess
B84: Tax WDV depreciation rate | C84: 0.4 | D84: /yr | E84: On eligible block
B85: Eligible block fraction | C85: 0.95 | D85: of project cost | E85: Balance on straight line
B86: Book depreciation life | C86: 25 | D86: years | E86: SLM
B87: Residual value | C87: 0.05
B89: H. BESS AUGMENTATION & MERCHANT
B90: Augmentation year | C90: 11 | E90: Full energy replacement per BESS spec
B91: Energy replacement fraction | C91: 1
B92: Augmentation cost | C92: 0.75 | D92: cr/MWh | E92: Future cell price
B93: Merchant price — year 1 | C93: 3.25 | D93: Rs/kWh
B94: Merchant escalation | C94: 0.02 | D94: /yr
B96: Sources: RFS.pdf, PROJECT CONFIGURATION_FDRE 2.docx, project_config_fdre2.json, engine fdre_enterprise_engine.py (v1.x, seed 42).

Sheet Capex
B1: Capex Build-Up & Financing (Rs cr)
B3: Component | C3: Rs cr | D3: Basis | F3: IDC schedule
B4: Solar EPC | C4: =Assumptions!$C$11*Assumptions!$C$40 -> 895.28 | D4: Solar MW x EPC rate | F4: Month | G4: Debt drawn (cum) | H4: Interest
B5: Wind EPC | C5: =Assumptions!$C$12*Assumptions!$C$41 -> 265.85 | D5: Wind MW x EPC rate | F5: 1 | G5: =0+$C$19*Assumptions!$C$74/12 -> 76.095228 | H5: =G5*$C$18 -> 0.53377847
B6: BESS energy | C6: =Assumptions!$C$14*Assumptions!$C$42 -> 594 | D6: MWh x rate | F6: 2 | G6: =G5+$C$19*Assumptions!$C$74/12 -> 152.19046 | H6: =G6*$C$18 -> 1.0675569
B7: BESS PCS | C7: =Assumptions!$C$13*Assumptions!$C$43 -> 54 | D7: MW x rate | F7: 3 | G7: =G6+$C$19*Assumptions!$C$74/12 -> 228.28569 | H7: =G7*$C$18 -> 1.6013354
B8: Land & development | C8: =Assumptions!$C$44+Assumptions!$C$11*Assumptions!$C$45+Assumptions!$C$12*Assumptions!$C$46+Assumptions!$C$14*Assumptions!$C$47 -> 234.032 | D8: Lump + per-asset land | F8: 4 | G8: =G7+$C$19*Assumptions!$C$74/12 -> 304.38091 | H8: =G8*$C$18 -> 2.1351139
B9: Transmission & connectivity | C9: =Assumptions!$C$48+C16*Assumptions!$C$49 -> 460 | D9: Lump + evacuation MW x rate | F9: 5 | G9: =G8+$C$19*Assumptions!$C$74/12 -> 380.47614 | H9: =G9*$C$18 -> 2.6688924
B10: Owner's costs | C10: =Assumptions!$C$51+(Assumptions!$C$11+Assumptions!$C$12+Assumptions!$C$13)*Assumptions!$C$52 -> 121.164 | D10: Lump + all-asset MW x rate | F10: 6 | G10: =G9+$C$19*Assumptions!$C$74/12 -> 456.57137 | H10: =G10*$C$18 -> 3.2026708
B11: Success charge | C11: =Assumptions!$C$15*Assumptions!$C$53*1.18/100 -> 2.36 | D11: Contracted MW x 1 lakh x GST | F11: 7 | G11: =G10+$C$19*Assumptions!$C$74/12 -> 532.6666 | H11: =G11*$C$18 -> 3.7364493
B12: Processing fee | C12: =Assumptions!$C$54*1.18/100 -> 0.118 | D12: Slab fee x GST | F12: 8 | G12: =G11+$C$19*Assumptions!$C$74/12 -> 608.76183 | H12: =G12*$C$18 -> 4.2702278
B13: Base capex | C13: =SUM(C4:C12) -> 2626.804 | F13: 9 | G13: =G12+$C$19*Assumptions!$C$74/12 -> 684.85706 | H13: =G13*$C$18 -> 4.8040062
B14: Contingency | C14: =C13*Assumptions!$C$55 -> 78.80412 | F14: 10 | G14: =G13+$C$19*Assumptions!$C$74/12 -> 760.95228 | H14: =G14*$C$18 -> 5.3377847
B15: HARD CAPEX | C15: =C13+C14 -> 2705.6081 | F15: 11 | G15: =G14+$C$19*Assumptions!$C$74/12 -> 837.04751 | H15: =G15*$C$18 -> 5.8715632
B16: Evacuation basis (MW) | C16: =MIN(MAX(Assumptions!$C$15,Assumptions!$C$11+Assumptions!$C$12,Assumptions!$C$13),Assumptions!$C$50) -> 280 | D16: min(max(contracted, RE MW, BESS MW), interconnection) | F16: 12 | G16: =G15+$C$19*Assumptions!$C$74/12 -> 913.14274 | H16: =G16*$C$18 -> 6.4053417
F17: 13 | G17: =G16+$C$19*Assumptions!$C$75/12 -> 1006.148 | H17: =G17*$C$18 -> 7.0577376
B18: Monthly interest rate | C18: =(1+Assumptions!$C$70)^(1/12)-1 -> 0.0070146116 | F18: 14 | G18: =G17+$C$19*Assumptions!$C$75/12 -> 1099.1533 | H18: =G18*$C$18 -> 7.7101335
B19: Debt base for IDC (hard x debt%) | C19: =C15*Assumptions!$C$69 -> 2029.2061 | F19: 15 | G19: =G18+$C$19*Assumptions!$C$75/12 -> 1192.1586 | H19: =G19*$C$18 -> 8.3625294
B20: IDC (capitalized) | C20: =SUM(H5:H28) -> 169.3857 | F20: 16 | G20: =G19+$C$19*Assumptions!$C$75/12 -> 1285.1639 | H20: =G20*$C$18 -> 9.0149253
B21: TOTAL PROJECT COST | C21: =C15+C20 -> 2874.9938 | F21: 17 | G21: =G20+$C$19*Assumptions!$C$75/12 -> 1378.1691 | H21: =G21*$C$18 -> 9.6673212
B22: Debt | C22: =C21*Assumptions!$C$69 -> 2156.2454 | F22: 18 | G22: =G21+$C$19*Assumptions!$C$75/12 -> 1471.1744 | H22: =G22*$C$18 -> 10.319717
B23: Equity | C23: =C21-C22 -> 718.74846 | F23: 19 | G23: =G22+$C$19*Assumptions!$C$75/12 -> 1564.1797 | H23: =G23*$C$18 -> 10.972113
F24: 20 | G24: =G23+$C$19*Assumptions!$C$75/12 -> 1657.185 | H24: =G24*$C$18 -> 11.624509
B25: EMD (capped Rs 10 cr) | C25: =MIN(0.0928*Assumptions!$C$11+0.1264*Assumptions!$C$12+0.1464*Assumptions!$C$13,10) -> 10 | D25: Rs 9.28/12.64/14.64 lakh per MW (solar/wind/ESS) | F25: 21 | G25: =G24+$C$19*Assumptions!$C$75/12 -> 1750.1903 | H25: =G25*$C$18 -> 12.276905
B26: PBG | C26: =0.232*Assumptions!$C$11+0.316*Assumptions!$C$12+0.366*Assumptions!$C$13 -> 145.806 | D26: Rs 23.20/31.60/36.60 lakh per MW | F26: 22 | G26: =G25+$C$19*Assumptions!$C$75/12 -> 1843.1955 | H26: =G26*$C$18 -> 12.929301
F27: 23 | G27: =G26+$C$19*Assumptions!$C$75/12 -> 1936.2008 | H27: =G27*$C$18 -> 13.581697
B28: BESS augmentation capex (year 11) | C28: =Assumptions!$C$14*Assumptions!$C$91*Assumptions!$C$92 -> 405 | F28: 24 | G28: =G27+$C$19*Assumptions!$C$75/12 -> 2029.2061 | H28: =G28*$C$18 -> 14.234093
F31: CHECK: debt fully repaid by yr-18 (closing balance, cr) | G31: ='Financial Model'!T51 -> 0
F32: Goal Seek this to 0 by changing Assumptions sculpting DSCR if assumptions change.

Sheet Dispatch 25Y
B1: 25-Year Dispatch & Annual Compliance (MWh)
G2: PPA cap =
B3: Year | C3: Solar gen | D3: Wind gen | E3: RE total | F3: Delivered at POI | G3: PPA target | H3: PPA energy | I3: Annual CUF | J3: Surplus | K3: Merchant sold | L3: CUF floor ok | M3: CUF cap ok | N3: Spill
B4: 1 | C4: =Assumptions!$C$11*Assumptions!$C$23*Assumptions!$C$31*Assumptions!$C$33*(1-Assumptions!$C$35)^(B4-1) -> 829267.96 | D4: =Assumptions!$C$12*Assumptions!$C$23*Assumptions!$C$32*Assumptions!$C$33*(1-Assumptions!$C$36)^(B4-1) -> 145200.21 | E4: =C4+D4 -> 974468.17 | F4: =E4*Assumptions!$C$34 -> 877021.35 | G4: =Assumptions!$C$19*Assumptions!$C$22*Assumptions!$C$15*Assumptions!$C$23 -> 701280 | H4: =MIN(F4,G4) -> 701280 | I4: =H4/(Assumptions!$C$15*Assumptions!$C$23) -> 0.4 | J4: =F4-H4 -> 175741.35 | K4: =J4*Assumptions!$C$37 -> 105444.81 | L4: =IF(I4>=Assumptions!$C$19*(1-Assumptions!$C$20),"PASS","FAIL") -> PASS | M4: =IF(I4<=Assumptions!$C$19*Assumptions!$C$21+0.0000001,"PASS","FAIL") -> PASS | N4: =J4-K4 -> 70296.54
B5: 2 | C5: =Assumptions!$C$11*Assumptions!$C$23*Assumptions!$C$31*Assumptions!$C$33*(1-Assumptions!$C$35)^(B5-1) -> 825121.62 | D5: =Assumptions!$C$12*Assumptions!$C$23*Assumptions!$C$32*Assumptions!$C$33*(1-Assumptions!$C$36)^(B5-1) -> 144909.8 | E5: =C5+D5 -> 970031.43 | F5: =E5*Assumptions!$C$34 -> 873028.28 | G5: =Assumptions!$C$19*Assumptions!$C$22*Assumptions!$C$15*Assumptions!$C$23 -> 701280 | H5: =MIN(F5,G5) -> 701280 | I5: =H5/(Assumptions!$C$15*Assumptions!$C$23) -> 0.4 | J5: =F5-H5 -> 171748.28 | K5: =J5*Assumptions!$C$37 -> 103048.97 | L5: =IF(I5>=Assumptions!$C$19*(1-Assumptions!$C$20),"PASS","FAIL") -> PASS | M5: =IF(I5<=Assumptions!$C$19*Assumptions!$C$21+0.0000001,"PASS","FAIL") -> PASS | N5: =J5-K5 -> 68699.314
B6: 3 | C6: =Assumptions!$C$11*Assumptions!$C$23*Assumptions!$C$31*Assumptions!$C$33*(1-Assumptions!$C$35)^(B6-1) -> 820996.01 | D6: =Assumptions!$C$12*Assumptions!$C$23*Assumptions!$C$32*Assumptions!$C$33*(1-Assumptions!$C$36)^(B6-1) -> 144619.99 | E6: =C6+D6 -> 965616 | F6: =E6*Assumptions!$C$34 -> 869054.4 | G6: =Assumptions!$C$19*Assumptions!$C$22*Assumptions!$C$15*Assumptions!$C$23 -> 701280 | H6: =MIN(F6,G6) -> 701280 | I6: =H6/(Assumptions!$C$15*Assumptions!$C$23) -> 0.4 | J6: =F6-H6 -> 167774.4 | K6: =J6*Assumptions!$C$37 -> 100664.64 | L6: =IF(I6>=Assumptions!$C$19*(1-Assumptions!$C$20),"PASS","FAIL") -> PASS | M6: =IF(I6<=Assumptions!$C$19*Assumptions!$C$21+0.0000001,"PASS","FAIL") -> PASS | N6: =J6-K6 -> 67109.76
B7: 4 | C7: =Assumptions!$C$11*Assumptions!$C$23*Assumptions!$C$31*Assumptions!$C$33*(1-Assumptions!$C$35)^(B7-1) -> 816891.03 | D7: =Assumptions!$C$12*Assumptions!$C$23*Assumptions!$C$32*Assumptions!$C$33*(1-Assumptions!$C$36)^(B7-1) -> 144330.75 | E7: =C7+D7 -> 961221.78 | F7: =E7*Assumptions!$C$34 -> 865099.6 | G7: =Assumptions!$C$19*Assumptions!$C$22*Assumptions!$C$15*Assumptions!$C$23 -> 701280 | H7: =MIN(F7,G7) -> 701280 | I7: =H7/(Assumptions!$C$15*Assumptions!$C$23) -> 0.4 | J7: =F7-H7 -> 163819.6 | K7: =J7*Assumptions!$C$37 -> 98291.761 | L7: =IF(I7>=Assumptions!$C$19*(1-Assumptions!$C$20),"PASS","FAIL") -> PASS | M7: =IF(I7<=Assumptions!$C$19*Assumptions!$C$21+0.0000001,"PASS","FAIL") -> PASS | N7: =J7-K7 -> 65527.841
B8: 5 | C8: =Assumptions!$C$11*Assumptions!$C$23*Assumptions!$C$31*Assumptions!$C$33*(1-Assumptions!$C$35)^(B8-1) -> 812806.58 | D8: =Assumptions!$C$12*Assumptions!$C$23*Assumptions!$C$32*Assumptions!$C$33*(1-Assumptions!$C$36)^(B8-1) -> 144042.08 | E8: =C8+D8 -> 956848.66 | F8: =E8*Assumptions!$C$34 -> 861163.8 | G8: =Assumptions!$C$19*Assumptions!$C$22*Assumptions!$C$15*Assumptions!$C$23 -> 701280 | H8: =MIN(F8,G8) -> 701280 | I8: =H8/(Assumptions!$C$15*Assumptions!$C$23) -> 0.4 | J8: =F8-H8 -> 159883.8 | K8: =J8*Assumptions!$C$37 -> 95930.278 | L8: =IF(I8>=Assumptions!$C$19*(1-Assumptions!$C$20),"PASS","FAIL") -> PASS | M8: =IF(I8<=Assumptions!$C$19*Assumptions!$C$21+0.0000001,"PASS","FAIL") -> PASS | N8: =J8-K8 -> 63953.519
B9: 6 | C9: =Assumptions!$C$11*Assumptions!$C$23*Assumptions!$C$31*Assumptions!$C$33*(1-Assumptions!$C$35)^(B9-1) -> 808742.55 | D9: =Assumptions!$C$12*Assumptions!$C$23*Assumptions!$C$32*Assumptions!$C$33*(1-Assumptions!$C$36)^(B9-1) -> 143754 | E9: =C9+D9 -> 952496.55 | F9: =E9*Assumptions!$C$34 -> 857246.89 | G9: =Assumptions!$C$19*Assumptions!$C$22*Assumptions!$C$15*Assumptions!$C$23 -> 701280 | H9: =MIN(F9,G9) -> 701280 | I9: =H9/(Assumptions!$C$15*Assumptions!$C$23) -> 0.4 | J9: =F9-H9 -> 155966.89 | K9: =J9*Assumptions!$C$37 -> 93580.135 | L9: =IF(I9>=Assumptions!$C$19*(1-Assumptions!$C$20),"PASS","FAIL") -> PASS | M9: =IF(I9<=Assumptions!$C$19*Assumptions!$C$21+0.0000001,"PASS","FAIL") -> PASS | N9: =J9-K9 -> 62386.756
B10: 7 | C10: =Assumptions!$C$11*Assumptions!$C$23*Assumptions!$C$31*Assumptions!$C$33*(1-Assumptions!$C$35)^(B10-1) -> 804698.83 | D10: =Assumptions!$C$12*Assumptions!$C$23*Assumptions!$C$32*Assumptions!$C$33*(1-Assumptions!$C$36)^(B10-1) -> 143466.49 | E10: =C10+D10 -> 948165.32 | F10: =E10*Assumptions!$C$34 -> 853348.79 | G10: =Assumptions!$C$19*Assumptions!$C$22*Assumptions!$C$15*Assumptions!$C$23 -> 701280 | H10: =MIN(F10,G10) -> 701280 | I10: =H10/(Assumptions!$C$15*Assumptions!$C$23) -> 0.4 | J10: =F10-H10 -> 152068.79 | K10: =J10*Assumptions!$C$37 -> 91241.275 | L10: =IF(I10>=Assumptions!$C$19*(1-Assumptions!$C$20),"PASS","FAIL") -> PASS | M10: =IF(I10<=Assumptions!$C$19*Assumptions!$C$21+0.0000001,"PASS","FAIL") -> PASS | N10: =J10-K10 -> 60827.517
B11: 8 | C11: =Assumptions!$C$11*Assumptions!$C$23*Assumptions!$C$31*Assumptions!$C$33*(1-Assumptions!$C$35)^(B11-1) -> 800675.34 | D11: =Assumptions!$C$12*Assumptions!$C$23*Assumptions!$C$32*Assumptions!$C$33*(1-Assumptions!$C$36)^(B11-1) -> 143179.56 | E11: =C11+D11 -> 943854.9 | F11: =E11*Assumptions!$C$34 -> 849469.41 | G11: =Assumptions!$C$19*Assumptions!$C$22*Assumptions!$C$15*Assumptions!$C$23 -> 701280 | H11: =MIN(F11,G11) -> 701280 | I11: =H11/(Assumptions!$C$15*Assumptions!$C$23) -> 0.4 | J11: =F11-H11 -> 148189.41 | K11: =J11*Assumptions!$C$37 -> 88913.645 | L11: =IF(I11>=Assumptions!$C$19*(1-Assumptions!$C$20),"PASS","FAIL") -> PASS | M11: =IF(I11<=Assumptions!$C$19*Assumptions!$C$21+0.0000001,"PASS","FAIL") -> PASS | N11: =J11-K11 -> 59275.763
B12: 9 | C12: =Assumptions!$C$11*Assumptions!$C$23*Assumptions!$C$31*Assumptions!$C$33*(1-Assumptions!$C$35)^(B12-1) -> 796671.96 | D12: =Assumptions!$C$12*Assumptions!$C$23*Assumptions!$C$32*Assumptions!$C$33*(1-Assumptions!$C$36)^(B12-1) -> 142893.2 | E12: =C12+D12 -> 939565.16 | F12: =E12*Assumptions!$C$34 -> 845608.65 | G12: =Assumptions!$C$19*Assumptions!$C$22*Assumptions!$C$15*Assumptions!$C$23 -> 701280 | H12: =MIN(F12,G12) -> 701280 | I12: =H12/(Assumptions!$C$15*Assumptions!$C$23) -> 0.4 | J12: =F12-H12 -> 144328.65 | K12: =J12*Assumptions!$C$37 -> 86597.187 | L12: =IF(I12>=Assumptions!$C$19*(1-Assumptions!$C$20),"PASS","FAIL") -> PASS | M12: =IF(I12<=Assumptions!$C$19*Assumptions!$C$21+0.0000001,"PASS","FAIL") -> PASS | N12: =J12-K12 -> 57731.458
B13: 10 | C13: =Assumptions!$C$11*Assumptions!$C$23*Assumptions!$C$31*Assumptions!$C$33*(1-Assumptions!$C$35)^(B13-1) -> 792688.6 | D13: =Assumptions!$C$12*Assumptions!$C$23*Assumptions!$C$32*Assumptions!$C$33*(1-Assumptions!$C$36)^(B13-1) -> 142607.41 | E13: =C13+D13 -> 935296.02 | F13: =E13*Assumptions!$C$34 -> 841766.41 | G13: =Assumptions!$C$19*Assumptions!$C$22*Assumptions!$C$15*Assumptions!$C$23 -> 701280 | H13: =MIN(F13,G13) -> 701280 | I13: =H13/(Assumptions!$C$15*Assumptions!$C$23) -> 0.4 | J13: =F13-H13 -> 140486.41 | K13: =J13*Assumptions!$C$37 -> 84291.848 | L13: =IF(I13>=Assumptions!$C$19*(1-Assumptions!$C$20),"PASS","FAIL") -> PASS | M13: =IF(I13<=Assumptions!$C$19*Assumptions!$C$21+0.0000001,"PASS","FAIL") -> PASS | N13: =J13-K13 -> 56194.566
B14: 11 | C14: =Assumptions!$C$11*Assumptions!$C$23*Assumptions!$C$31*Assumptions!$C$33*(1-Assumptions!$C$35)^(B14-1) -> 788725.16 | D14: =Assumptions!$C$12*Assumptions!$C$23*Assumptions!$C$32*Assumptions!$C$33*(1-Assumptions!$C$36)^(B14-1) -> 142322.2 | E14: =C14+D14 -> 931047.36 | F14: =E14*Assumptions!$C$34 -> 837942.62 | G14: =Assumptions!$C$19*Assumptions!$C$22*Assumptions!$C$15*Assumptions!$C$23 -> 701280 | H14: =MIN(F14,G14) -> 701280 | I14: =H14/(Assumptions!$C$15*Assumptions!$C$23) -> 0.4 | J14: =F14-H14 -> 136662.62 | K14: =J14*Assumptions!$C$37 -> 81997.573 | L14: =IF(I14>=Assumptions!$C$19*(1-Assumptions!$C$20),"PASS","FAIL") -> PASS | M14: =IF(I14<=Assumptions!$C$19*Assumptions!$C$21+0.0000001,"PASS","FAIL") -> PASS | N14: =J14-K14 -> 54665.049
B15: 12 | C15: =Assumptions!$C$11*Assumptions!$C$23*Assumptions!$C$31*Assumptions!$C$33*(1-Assumptions!$C$35)^(B15-1) -> 784781.53 | D15: =Assumptions!$C$12*Assumptions!$C$23*Assumptions!$C$32*Assumptions!$C$33*(1-Assumptions!$C$36)^(B15-1) -> 142037.55 | E15: =C15+D15 -> 926819.09 | F15: =E15*Assumptions!$C$34 -> 834137.18 | G15: =Assumptions!$C$19*Assumptions!$C$22*Assumptions!$C$15*Assumptions!$C$23 -> 701280 | H15: =MIN(F15,G15) -> 701280 | I15: =H15/(Assumptions!$C$15*Assumptions!$C$23) -> 0.4 | J15: =F15-H15 -> 132857.18 | K15: =J15*Assumptions!$C$37 -> 79714.307 | L15: =IF(I15>=Assumptions!$C$19*(1-Assumptions!$C$20),"PASS","FAIL") -> PASS | M15: =IF(I15<=Assumptions!$C$19*Assumptions!$C$21+0.0000001,"PASS","FAIL") -> PASS | N15: =J15-K15 -> 53142.872
... B28: 25 | C28: =Assumptions!$C$11*Assumptions!$C$23*Assumptions!$C$31*Assumptions!$C$33*(1-Assumptions!$C$35)^(B28-1) -> 735273.35 | D28: =Assumptions!$C$12*Assumptions!$C$23*Assumptions!$C$32*Assumptions!$C$33*(1-Assumptions!$C$36)^(B28-1) -> 138388.57 | E28: =C28+D28 -> 873661.92 | F28: =E28*Assumptions!$C$34 -> 786295.73 | G28: =Assumptions!$C$19*Assumptions!$C$22*Assumptions!$C$15*Assumptions!$C$23 -> 701280 | H28: =MIN(F28,G28) -> 701280 | I28: =H28/(Assumptions!$C$15*Assumptions!$C$23) -> 0.4 | J28: =F28-H28 -> 85015.728 | K28: =J28*Assumptions!$C$37 -> 51009.437 | L28: =IF(I28>=Assumptions!$C$19*(1-Assumptions!$C$20),"PASS","FAIL") -> PASS | M28: =IF(I28<=Assumptions!$C$19*Assumptions!$C$21+0.0000001,"PASS","FAIL") -> PASS | N28: =J28-K28 -> 34006.291
B29: Scenario: PPA delivery held at the DECLARED CUF (40%) in all 25 years — inside the -15%/+10% band throughout. Surplus RE above the target is sold merchant at the capture factor. Set the offtake lever to 1.10 to model delivery at the +10% cap.

Sheet Monthly Y1
B1: Year-1 Monthly Dispatch & Peak Compliance
B3: Month | C3: Days | D3: Peak hours | E3: Peak obligation MWh | F3: Availability % | G3: Peak delivered MWh | H3: Floor (90%) MWh | I3: Shortfall MWh | J3: LD Rs cr | K3: Compliant | L3: PPA energy MWh | M3: Monthly CUF
B4: Jan | C4: 31 | D4: =C4*Assumptions!$C$25 -> 124 | E4: =D4*Assumptions!$C$15 -> 24800 | F4: 0.9 | G4: =E4*F4 -> 22320 | H4: =E4*Assumptions!$C$24 -> 22320 | I4: =MAX(0,H4-G4) -> 0 | J4: =I4*Assumptions!$C$26*Assumptions!$C$16/10000 -> 0 | K4: =IF(F4>=Assumptions!$C$24,"PASS","FAIL") -> PASS | L4: ='Dispatch 25Y'!H4*C4/365 -> 59560.767 | M4: =L4/(Assumptions!$C$15*C4*24) -> 0.40027397
B5: Feb | C5: 28 | D5: =C5*Assumptions!$C$25 -> 112 | E5: =D5*Assumptions!$C$15 -> 22400 | F5: 0.9 | G5: =E5*F5 -> 20160 | H5: =E5*Assumptions!$C$24 -> 20160 | I5: =MAX(0,H5-G5) -> 0 | J5: =I5*Assumptions!$C$26*Assumptions!$C$16/10000 -> 0 | K5: =IF(F5>=Assumptions!$C$24,"PASS","FAIL") -> PASS | L5: ='Dispatch 25Y'!H4*C5/365 -> 53796.822 | M5: =L5/(Assumptions!$C$15*C5*24) -> 0.40027397
B6: Mar | C6: 31 | D6: =C6*Assumptions!$C$25 -> 124 | E6: =D6*Assumptions!$C$15 -> 24800 | F6: 0.9 | G6: =E6*F6 -> 22320 | H6: =E6*Assumptions!$C$24 -> 22320 | I6: =MAX(0,H6-G6) -> 0 | J6: =I6*Assumptions!$C$26*Assumptions!$C$16/10000 -> 0 | K6: =IF(F6>=Assumptions!$C$24,"PASS","FAIL") -> PASS | L6: ='Dispatch 25Y'!H4*C6/365 -> 59560.767 | M6: =L6/(Assumptions!$C$15*C6*24) -> 0.40027397
B7: Apr | C7: 30 | D7: =C7*Assumptions!$C$25 -> 120 | E7: =D7*Assumptions!$C$15 -> 24000 | F7: 0.9 | G7: =E7*F7 -> 21600 | H7: =E7*Assumptions!$C$24 -> 21600 | I7: =MAX(0,H7-G7) -> 0 | J7: =I7*Assumptions!$C$26*Assumptions!$C$16/10000 -> 0 | K7: =IF(F7>=Assumptions!$C$24,"PASS","FAIL") -> PASS | L7: ='Dispatch 25Y'!H4*C7/365 -> 57639.452 | M7: =L7/(Assumptions!$C$15*C7*24) -> 0.40027397
B8: May | C8: 31 | D8: =C8*Assumptions!$C$25 -> 124 | E8: =D8*Assumptions!$C$15 -> 24800 | F8: 0.9 | G8: =E8*F8 -> 22320 | H8: =E8*Assumptions!$C$24 -> 22320 | I8: =MAX(0,H8-G8) -> 0 | J8: =I8*Assumptions!$C$26*Assumptions!$C$16/10000 -> 0 | K8: =IF(F8>=Assumptions!$C$24,"PASS","FAIL") -> PASS | L8: ='Dispatch 25Y'!H4*C8/365 -> 59560.767 | M8: =L8/(Assumptions!$C$15*C8*24) -> 0.40027397
B9: Jun | C9: 30 | D9: =C9*Assumptions!$C$25 -> 120 | E9: =D9*Assumptions!$C$15 -> 24000 | F9: 0.9 | G9: =E9*F9 -> 21600 | H9: =E9*Assumptions!$C$24 -> 21600 | I9: =MAX(0,H9-G9) -> 0 | J9: =I9*Assumptions!$C$26*Assumptions!$C$16/10000 -> 0 | K9: =IF(F9>=Assumptions!$C$24,"PASS","FAIL") -> PASS | L9: ='Dispatch 25Y'!H4*C9/365 -> 57639.452 | M9: =L9/(Assumptions!$C$15*C9*24) -> 0.40027397
B10: Jul | C10: 31 | D10: =C10*Assumptions!$C$25 -> 124 | E10: =D10*Assumptions!$C$15 -> 24800 | F10: 0.9 | G10: =E10*F10 -> 22320 | H10: =E10*Assumptions!$C$24 -> 22320 | I10: =MAX(0,H10-G10) -> 0 | J10: =I10*Assumptions!$C$26*Assumptions!$C$16/10000 -> 0 | K10: =IF(F10>=Assumptions!$C$24,"PASS","FAIL") -> PASS | L10: ='Dispatch 25Y'!H4*C10/365 -> 59560.767 | M10: =L10/(Assumptions!$C$15*C10*24) -> 0.40027397
B11: Aug | C11: 31 | D11: =C11*Assumptions!$C$25 -> 124 | E11: =D11*Assumptions!$C$15 -> 24800 | F11: 0.9 | G11: =E11*F11 -> 22320 | H11: =E11*Assumptions!$C$24 -> 22320 | I11: =MAX(0,H11-G11) -> 0 | J11: =I11*Assumptions!$C$26*Assumptions!$C$16/10000 -> 0 | K11: =IF(F11>=Assumptions!$C$24,"PASS","FAIL") -> PASS | L11: ='Dispatch 25Y'!H4*C11/365 -> 59560.767 | M11: =L11/(Assumptions!$C$15*C11*24) -> 0.40027397
B12: Sep | C12: 30 | D12: =C12*Assumptions!$C$25 -> 120 | E12: =D12*Assumptions!$C$15 -> 24000 | F12: 0.9 | G12: =E12*F12 -> 21600 | H12: =E12*Assumptions!$C$24 -> 21600 | I12: =MAX(0,H12-G12) -> 0 | J12: =I12*Assumptions!$C$26*Assumptions!$C$16/10000 -> 0 | K12: =IF(F12>=Assumptions!$C$24,"PASS","FAIL") -> PASS | L12: ='Dispatch 25Y'!H4*C12/365 -> 57639.452 | M12: =L12/(Assumptions!$C$15*C12*24) -> 0.40027397
B13: Oct | C13: 31 | D13: =C13*Assumptions!$C$25 -> 124 | E13: =D13*Assumptions!$C$15 -> 24800 | F13: 0.9 | G13: =E13*F13 -> 22320 | H13: =E13*Assumptions!$C$24 -> 22320 | I13: =MAX(0,H13-G13) -> 0 | J13: =I13*Assumptions!$C$26*Assumptions!$C$16/10000 -> 0 | K13: =IF(F13>=Assumptions!$C$24,"PASS","FAIL") -> PASS | L13: ='Dispatch 25Y'!H4*C13/365 -> 59560.767 | M13: =L13/(Assumptions!$C$15*C13*24) -> 0.40027397
B14: Nov | C14: 30 | D14: =C14*Assumptions!$C$25 -> 120 | E14: =D14*Assumptions!$C$15 -> 24000 | F14: 0.9 | G14: =E14*F14 -> 21600 | H14: =E14*Assumptions!$C$24 -> 21600 | I14: =MAX(0,H14-G14) -> 0 | J14: =I14*Assumptions!$C$26*Assumptions!$C$16/10000 -> 0 | K14: =IF(F14>=Assumptions!$C$24,"PASS","FAIL") -> PASS | L14: ='Dispatch 25Y'!H4*C14/365 -> 57639.452 | M14: =L14/(Assumptions!$C$15*C14*24) -> 0.40027397
B15: Dec | C15: 31 | D15: =C15*Assumptions!$C$25 -> 124 | E15: =D15*Assumptions!$C$15 -> 24800 | F15: 0.9 | G15: =E15*F15 -> 22320 | H15: =E15*Assumptions!$C$24 -> 22320 | I15: =MAX(0,H15-G15) -> 0 | J15: =I15*Assumptions!$C$26*Assumptions!$C$16/10000 -> 0 | K15: =IF(F15>=Assumptions!$C$24,"PASS","FAIL") -> PASS | L15: ='Dispatch 25Y'!H4*C15/365 -> 59560.767 | M15: =L15/(Assumptions!$C$15*C15*24) -> 0.40027397
B16: TOTAL / MIN | C16: =SUM(C4:C15) -> 365 | E16: =SUM(E4:E15) -> 292000 | F16: =MIN(F4:F15) -> 0.9 | I16: =SUM(I4:I15) -> 0 | J16: =SUM(J4:J15) -> 0 | K16: =IF(COUNTIF(K4:K15,"FAIL")=0,"ALL PASS","FAIL") -> ALL PASS | L16: =SUM(L4:L15) -> 701280
B18: Scenario: availability held at the 90% RfS floor in every month (blue inputs) — exactly compliant, zero liquidated damages. Replace with monthly dispatch output when re-running the engine.

Sheet Financial Model
B1: 25-Year Financial Model (Rs cr unless noted)
B2: Year | C2: 1 | D2: 2 | E2: 3 | F2: 4 | G2: 5 | H2: 6 | I2: 7 | J2: 8 | K2: 9 | L2: 10 | M2: 11 | N2: 12 | O2: 13 | P2: 14 | Q2: 15 | R2: 16 | S2: 17 | T2: 18 | U2: 19 | V2: 20 | W2: 21 | X2: 22 | Y2: 23 | Z2: 24 | AA2: 25
B4: ENERGY
B5: PPA energy (MWh) | C5: ='Dispatch 25Y'!H4 -> 701280 | D5: ='Dispatch 25Y'!H5 -> 701280 | E5: ='Dispatch 25Y'!H6 -> 701280 | F5: ='Dispatch 25Y'!H7 -> 701280 | G5: ='Dispatch 25Y'!H8 -> 701280 | H5: ='Dispatch 25Y'!H9 -> 701280 | I5: ='Dispatch 25Y'!H10 -> 701280 | J5: ='Dispatch 25Y'!H11 -> 701280 | K5: ='Dispatch 25Y'!H12 -> 701280 | L5: ='Dispatch 25Y'!H13 -> 701280 | M5: ='Dispatch 25Y'!H14 -> 701280 | N5: ='Dispatch 25Y'!H15 -> 701280 | O5: ='Dispatch 25Y'!H16 -> 701280 | P5: ='Dispatch 25Y'!H17 -> 701280 | Q5: ='Dispatch 25Y'!H18 -> 701280 | R5: ='Dispatch 25Y'!H19 -> 701280 | S5: ='Dispatch 25Y'!H20 -> 701280 | T5: ='Dispatch 25Y'!H21 -> 701280 | U5: ='Dispatch 25Y'!H22 -> 701280 | V5: ='Dispatch 25Y'!H23 -> 701280 | W5: ='Dispatch 25Y'!H24 -> 701280 | X5: ='Dispatch 25Y'!H25 -> 701280 | Y5: ='Dispatch 25Y'!H26 -> 701280 | Z5: ='Dispatch 25Y'!H27 -> 701280 | AA5: ='Dispatch 25Y'!H28 -> 701280
B6: Merchant energy (MWh) | C6: ='Dispatch 25Y'!K4 -> 105444.81 | D6: ='Dispatch 25Y'!K5 -> 103048.97 | E6: ='Dispatch 25Y'!K6 -> 100664.64 | F6: ='Dispatch 25Y'!K7 -> 98291.761 | G6: ='Dispatch 25Y'!K8 -> 95930.278 | H6: ='Dispatch 25Y'!K9 -> 93580.135 | I6: ='Dispatch 25Y'!K10 -> 91241.275 | J6: ='Dispatch 25Y'!K11 -> 88913.645 | K6: ='Dispatch 25Y'!K12 -> 86597.187 | L6: ='Dispatch 25Y'!K13 -> 84291.848 | M6: ='Dispatch 25Y'!K14 -> 81997.573 | N6: ='Dispatch 25Y'!K15 -> 79714.307 | O6: ='Dispatch 25Y'!K16 -> 77441.997 | P6: ='Dispatch 25Y'!K17 -> 75180.587 | Q6: ='Dispatch 25Y'!K18 -> 72930.026 | R6: ='Dispatch 25Y'!K19 -> 70690.259 | S6: ='Dispatch 25Y'!K20 -> 68461.233 | T6: ='Dispatch 25Y'!K21 -> 66242.896 | U6: ='Dispatch 25Y'!K22 -> 64035.195 | V6: ='Dispatch 25Y'!K23 -> 61838.077 | W6: ='Dispatch 25Y'!K24 -> 59651.492 | X6: ='Dispatch 25Y'!K25 -> 57475.386 | Y6: ='Dispatch 25Y'!K26 -> 55309.709 | Z6: ='Dispatch 25Y'!K27 -> 53154.41 | AA6: ='Dispatch 25Y'!K28 -> 51009.437
B8: REVENUE
B9: Net PPA tariff (Rs/kWh, tariff - PSM) | C9: =Assumptions!$C$16-Assumptions!$C$27 -> 5.8913 | D9: =Assumptions!$C$16-Assumptions!$C$27 -> 5.8913 | E9: =Assumptions!$C$16-Assumptions!$C$27 -> 5.8913 | F9: =Assumptions!$C$16-Assumptions!$C$27 -> 5.8913 | G9: =Assumptions!$C$16-Assumptions!$C$27 -> 5.8913 | H9: =Assumptions!$C$16-Assumptions!$C$27 -> 5.8913 | I9: =Assumptions!$C$16-Assumptions!$C$27 -> 5.8913 | J9: =Assumptions!$C$16-Assumptions!$C$27 -> 5.8913 | ... AA9: =Assumptions!$C$16-Assumptions!$C$27 -> 5.8913
B10: PPA revenue | C10: =C5*C9/10000 -> 413.14509 | D10: =D5*D9/10000 -> 413.14509 | E10: =E5*E9/10000 -> 413.14509 | F10: =F5*F9/10000 -> 413.14509 | G10: =G5*G9/10000 -> 413.14509 | H10: =H5*H9/10000 -> 413.14509 | I10: =I5*I9/10000 -> 413.14509 | J10: =J5*J9/10000 -> 413.14509 | ... AA10: =AA5*AA9/10000 -> 413.14509
B11: Merchant price (Rs/kWh) | C11: =Assumptions!$C$93*(1+Assumptions!$C$94)^(C2-1) -> 3.25 | D11: =Assumptions!$C$93*(1+Assumptions!$C$94)^(D2-1) -> 3.315 | E11: =Assumptions!$C$93*(1+Assumptions!$C$94)^(E2-1) -> 3.3813 | F11: =Assumptions!$C$93*(1+Assumptions!$C$94)^(F2-1) -> 3.448926 | G11: =Assumptions!$C$93*(1+Assumptions!$C$94)^(G2-1) -> 3.5179045 | H11: =Assumptions!$C$93*(1+Assumptions!$C$94)^(H2-1) -> 3.5882626 | I11: =Assumptions!$C$93*(1+Assumptions!$C$94)^(I2-1) -> 3.6600279 | J11: =Assumptions!$C$93*(1+Assumptions!$C$94)^(J2-1) -> 3.7332284 | ... AA11: =Assumptions!$C$93*(1+Assumptions!$C$94)^(AA2-1) -> 5.2274211
B12: Merchant revenue | C12: =C6*C11/10000 -> 34.269563 | D12: =D6*D11/10000 -> 34.160734 | E12: =E6*E11/10000 -> 34.037735 | F12: =F6*F11/10000 -> 33.900101 | G12: =G6*G11/10000 -> 33.747356 | H12: =H6*H11/10000 -> 33.57901 | I12: =I6*I11/10000 -> 33.394561 | J12: =J6*J11/10000 -> 33.193495 | ... AA12: =AA6*AA11/10000 -> 26.66478
B13: Total revenue | C13: =C10+C12 -> 447.41465 | D13: =D10+D12 -> 447.30582 | E13: =E10+E12 -> 447.18282 | F13: =F10+F12 -> 447.04519 | G13: =G10+G12 -> 446.89244 | H13: =H10+H12 -> 446.7241 | I13: =I10+I12 -> 446.53965 | J13: =J10+J12 -> 446.33858 | ... AA13: =AA10+AA12 -> 439.80987
B15: OPERATING EXPENSES
B16: Generation + BESS O&M (escalated) | C16: =((Assumptions!$C$11*Assumptions!$C$58+Assumptions!$C$12*Assumptions!$C$59+Assumptions!$C$14*Assumptions!$C$60)/100)*(1+Assumptions!$C$65)^(C2-1) -> 26.863 | D16: =((Assumptions!$C$11*Assumptions!$C$58+Assumptions!$C$12*Assumptions!$C$59+Assumptions!$C$14*Assumptions!$C$60)/100)*(1+Assumptions!$C$65)^(D2-1) -> 27.803205 | E16: =((Assumptions!$C$11*Assumptions!$C$58+Assumptions!$C$12*Assumptions!$C$59+Assumptions!$C$14*Assumptions!$C$60)/100)*(1+Assumptions!$C$65)^(E2-1) -> 28.776317 | F16: =((Assumptions!$C$11*Assumptions!$C$58+Assumptions!$C$12*Assumptions!$C$59+Assumptions!$C$14*Assumptions!$C$60)/100)*(1+Assumptions!$C$65)^(F2-1) -> 29.783488 | G16: =((Assumptions!$C$11*Assumptions!$C$58+Assumptions!$C$12*Assumptions!$C$59+Assumptions!$C$14*Assumptions!$C$60)/100)*(1+Assumptions!$C$65)^(G2-1) -> 30.82591 | H16: =((Assumptions!$C$11*Assumptions!$C$58+Assumptions!$C$12*Assumptions!$C$59+Assumptions!$C$14*Assumptions!$C$60)/100)*(1+Assumptions!$C$65)^(H2-1) -> 31.904817 | I16: =((Assumptions!$C$11*Assumptions!$C$58+Assumptions!$C$12*Assumptions!$C$59+Assumptions!$C$14*Assumptions!$C$60)/100)*(1+Assumptions!$C$65)^(I2-1) -> 33.021486 | J16: =((Assumptions!$C$11*Assumptions!$C$58+Assumptions!$C$12*Assumptions!$C$59+Assumptions!$C$14*Assumptions!$C$60)/100)*(1+Assumptions!$C$65)^(J2-1) -> 34.177238 | ... AA16: =((Assumptions!$C$11*Assumptions!$C$58+Assumptions!$C$12*Assumptions!$C$59+Assumptions!$C$14*Assumptions!$C$60)/100)*(1+Assumptions!$C$65)^(AA2-1) -> 61.337053
B17: Admin (escalated) | C17: =(Assumptions!$C$61+(Assumptions!$C$11+Assumptions!$C$12+Assumptions!$C$13)*Assumptions!$C$62/100)*(1+Assumptions!$C$65)^(C2-1) -> 8.82275 | D17: =(Assumptions!$C$61+(Assumptions!$C$11+Assumptions!$C$12+Assumptions!$C$13)*Assumptions!$C$62/100)*(1+Assumptions!$C$65)^(D2-1) -> 9.1315462 | E17: =(Assumptions!$C$61+(Assumptions!$C$11+Assumptions!$C$12+Assumptions!$C$13)*Assumptions!$C$62/100)*(1+Assumptions!$C$65)^(E2-1) -> 9.4511504 | F17: =(Assumptions!$C$61+(Assumptions!$C$11+Assumptions!$C$12+Assumptions!$C$13)*Assumptions!$C$62/100)*(1+Assumptions!$C$65)^(F2-1) -> 9.7819406 | G17: =(Assumptions!$C$61+(Assumptions!$C$11+Assumptions!$C$12+Assumptions!$C$13)*Assumptions!$C$62/100)*(1+Assumptions!$C$65)^(G2-1) -> 10.124309 | H17: =(Assumptions!$C$61+(Assumptions!$C$11+Assumptions!$C$12+Assumptions!$C$13)*Assumptions!$C$62/100)*(1+Assumptions!$C$65)^(H2-1) -> 10.478659 | I17: =(Assumptions!$C$61+(Assumptions!$C$11+Assumptions!$C$12+Assumptions!$C$13)*Assumptions!$C$62/100)*(1+Assumptions!$C$65)^(I2-1) -> 10.845412 | J17: =(Assumptions!$C$61+(Assumptions!$C$11+Assumptions!$C$12+Assumptions!$C$13)*Assumptions!$C$62/100)*(1+Assumptions!$C$65)^(J2-1) -> 11.225002 | ... AA17: =(Assumptions!$C$61+(Assumptions!$C$11+Assumptions!$C$12+Assumptions!$C$13)*Assumptions!$C$62/100)*(1+Assumptions!$C$65)^(AA2-1) -> 20.145236
B18: Transmission O&M (escalated) | C18: =Capex!$C$16*Assumptions!$C$63/100*(1+Assumptions!$C$65)^(C2-1) -> 5.6 | D18: =Capex!$C$16*Assumptions!$C$63/100*(1+Assumptions!$C$65)^(D2-1) -> 5.796 | E18: =Capex!$C$16*Assumptions!$C$63/100*(1+Assumptions!$C$65)^(E2-1) -> 5.99886 | F18: =Capex!$C$16*Assumptions!$C$63/100*(1+Assumptions!$C$65)^(F2-1) -> 6.2088201 | G18: =Capex!$C$16*Assumptions!$C$63/100*(1+Assumptions!$C$65)^(G2-1) -> 6.4261288 | H18: =Capex!$C$16*Assumptions!$C$63/100*(1+Assumptions!$C$65)^(H2-1) -> 6.6510433 | I18: =Capex!$C$16*Assumptions!$C$63/100*(1+Assumptions!$C$65)^(I2-1) -> 6.8838298 | J18: =Capex!$C$16*Assumptions!$C$63/100*(1+Assumptions!$C$65)^(J2-1) -> 7.1247639 | ... AA18: =Capex!$C$16*Assumptions!$C$63/100*(1+Assumptions!$C$65)^(AA2-1) -> 12.78664
B19: Insurance (on hard capex) | C19: =Capex!$C$15*Assumptions!$C$64 -> 9.4696284 | D19: =Capex!$C$15*Assumptions!$C$64 -> 9.4696284 | E19: =Capex!$C$15*Assumptions!$C$64 -> 9.4696284 | F19: =Capex!$C$15*Assumptions!$C$64 -> 9.4696284 | G19: =Capex!$C$15*Assumptions!$C$64 -> 9.4696284 | H19: =Capex!$C$15*Assumptions!$C$64 -> 9.4696284 | I19: =Capex!$C$15*Assumptions!$C$64 -> 9.4696284 | J19: =Capex!$C$15*Assumptions!$C$64 -> 9.4696284 | ... AA19: =Capex!$C$15*Assumptions!$C$64 -> 9.4696284
B20: Working-capital interest | C20: =MAX(C13,0)*Assumptions!$C$79/365*Assumptions!$C$80 -> 6.9870233 | D20: =MAX(D13,0)*Assumptions!$C$79/365*Assumptions!$C$80 -> 6.9853238 | E20: =MAX(E13,0)*Assumptions!$C$79/365*Assumptions!$C$80 -> 6.983403 | F20: =MAX(F13,0)*Assumptions!$C$79/365*Assumptions!$C$80 -> 6.9812536 | G20: =MAX(G13,0)*Assumptions!$C$79/365*Assumptions!$C$80 -> 6.9788683 | H20: =MAX(H13,0)*Assumptions!$C$79/365*Assumptions!$C$80 -> 6.9762393 | I20: =MAX(I13,0)*Assumptions!$C$79/365*Assumptions!$C$80 -> 6.9733589 | J20: =MAX(J13,0)*Assumptions!$C$79/365*Assumptions!$C$80 -> 6.9702189 | ... AA20: =MAX(AA13,0)*Assumptions!$C$79/365*Assumptions!$C$80 -> 6.8682637
B21: Transmission losses (on PPA revenue) | C21: =C10*Assumptions!$C$66 -> 2.0657254 | D21: =D10*Assumptions!$C$66 -> 2.0657254 | E21: =E10*Assumptions!$C$66 -> 2.0657254 | F21: =F10*Assumptions!$C$66 -> 2.0657254 | G21: =G10*Assumptions!$C$66 -> 2.0657254 | H21: =H10*Assumptions!$C$66 -> 2.0657254 | I21: =I10*Assumptions!$C$66 -> 2.0657254 | J21: =J10*Assumptions!$C$66 -> 2.0657254 | ... AA21: =AA10*Assumptions!$C$66 -> 2.0657254
B22: Total opex | C22: =SUM(C16:C21) -> 59.808127 | D22: =SUM(D16:D21) -> 61.251429 | E22: =SUM(E16:E21) -> 62.745084 | F22: =SUM(F16:F21) -> 64.290856 | G22: =SUM(G16:G21) -> 65.89057 | H22: =SUM(H16:H21) -> 67.546113 | I22: =SUM(I16:I21) -> 69.259441 | J22: =SUM(J16:J21) -> 71.032576 | ... AA22: =SUM(AA16:AA21) -> 112.67255
B23: EBITDA | C23: =C13-C22 -> 387.60652 | D23: =D13-D22 -> 386.05439 | E23: =E13-E22 -> 384.43774 | F23: =F13-F22 -> 382.75433 | G23: =G13-G22 -> 381.00187 | H23: =H13-H22 -> 379.17798 | I23: =I13-I22 -> 377.28021 | J23: =J13-J22 -> 375.306 | ... AA23: =AA13-AA22 -> 327.13732
B25: TAX COMPUTATION (Sec 115BAA, WDV + loss carry-forward)
B26: WDV block — opening | C26: =Capex!$C$21*Assumptions!$C$85 -> 2731.2441 | D26: =C29 -> 1638.7465 | E26: =D29 -> 983.24789 | F26: =E29 -> 589.94873 | G26: =F29 -> 353.96924 | H26: =G29 -> 212.38154 | I26: =H29 -> 127.42893 | J26: =I29 -> 76.457356 | K26: =J29 -> 45.874413 | ... AA26: =Z29 -> 0.3144478
B27: Addition (augmentation x eligible) | C27: =IF(C2=Assumptions!$C$90,Capex!$C$28*Assumptions!$C$85,0) -> 0 | D27: =IF(D2=Assumptions!$C$90,Capex!$C$28*Assumptions!$C$85,0) -> 0 | E27: =IF(E2=Assumptions!$C$90,Capex!$C$28*Assumptions!$C$85,0) -> 0 | F27: =IF(F2=Assumptions!$C$90,Capex!$C$28*Assumptions!$C$85,0) -> 0 | G27: =IF(G2=Assumptions!$C$90,Capex!$C$28*Assumptions!$C$85,0) -> 0 | H27: =IF(H2=Assumptions!$C$90,Capex!$C$28*Assumptions!$C$85,0) -> 0 | I27: =IF(I2=Assumptions!$C$90,Capex!$C$28*Assumptions!$C$85,0) -> 0 | J27: =IF(J2=Assumptions!$C$90,Capex!$C$28*Assumptions!$C$85,0) -> 0 | ... AA27: =IF(AA2=Assumptions!$C$90,Capex!$C$28*Assumptions!$C$85,0) -> 0
B28: WDV depreciation (40%) | C28: =(C26+C27)*Assumptions!$C$84 -> 1092.4977 | D28: =(D26+D27)*Assumptions!$C$84 -> 655.49859 | E28: =(E26+E27)*Assumptions!$C$84 -> 393.29915 | F28: =(F26+F27)*Assumptions!$C$84 -> 235.97949 | G28: =(G26+G27)*Assumptions!$C$84 -> 141.5877 | H28: =(H26+H27)*Assumptions!$C$84 -> 84.952617 | I28: =(I26+I27)*Assumptions!$C$84 -> 50.97157 | J28: =(J26+J27)*Assumptions!$C$84 -> 30.582942 | ... AA28: =(AA26+AA27)*Assumptions!$C$84 -> 0.12577912
B29: WDV block — closing | C29: =C26+C27-C28 -> 1638.7465 | D29: =D26+D27-D28 -> 983.24789 | E29: =E26+E27-E28 -> 589.94873 | F29: =F26+F27-F28 -> 353.96924 | G29: =G26+G27-G28 -> 212.38154 | H29: =H26+H27-H28 -> 127.42893 | I29: =I26+I27-I28 -> 76.457356 | J29: =J26+J27-J28 -> 45.874413 | ... AA29: =AA26+AA27-AA28 -> 0.18866868
B30: SLM on non-eligible 5% | C30: =Capex!$C$21*(1-Assumptions!$C$85)/Assumptions!$C$86 -> 5.7499876 | D30: =Capex!$C$21*(1-Assumptions!$C$85)/Assumptions!$C$86 -> 5.7499876 | E30: =Capex!$C$21*(1-Assumptions!$C$85)/Assumptions!$C$86 -> 5.7499876 | F30: =Capex!$C$21*(1-Assumptions!$C$85)/Assumptions!$C$86 -> 5.7499876 | G30: =Capex!$C$21*(1-Assumptions!$C$85)/Assumptions!$C$86 -> 5.7499876 | H30: =Capex!$C$21*(1-Assumptions!$C$85)/Assumptions!$C$86 -> 5.7499876 | I30: =Capex!$C$21*(1-Assumptions!$C$85)/Assumptions!$C$86 -> 5.7499876 | J30: =Capex!$C$21*(1-Assumptions!$C$85)/Assumptions!$C$86 -> 5.7499876 | ... AA30: =Capex!$C$21*(1-Assumptions!$C$85)/Assumptions!$C$86 -> 5.7499876
B31: Total tax depreciation | C31: =C28+C30 -> 1098.2476 | D31: =D28+D30 -> 661.24858 | E31: =E28+E30 -> 399.04914 | F31: =F28+F30 -> 241.72948 | G31: =G28+G30 -> 147.33768 | H31: =H28+H30 -> 90.702605 | I31: =I28+I30 -> 56.721558 | J31: =J28+J30 -> 36.33293 | ... AA31: =AA28+AA30 -> 5.8757668
B32: Taxable income (EBITDA - interest - tax dep) | C32: =C23-C47-C31 -> -899.31259 | D32: =D23-D47-D31 -> -461.78431 | E32: =E23-E47-E31 -> -194.67536 | F32: =F23-F47-F31 -> -32.037461 | G32: =G23-G47-G31 -> 68.116662 | H32: =H23-H47-H31 -> 130.99659 | I32: =I23-I47-I31 -> 171.74681 | J32: =J23-J47-J31 -> 199.47436 | ... AA32: =AA23-AA47-AA31 -> 321.26155
B33: Loss brought forward | C33: =0 -> 0 | D33: =C36 -> 899.31259 | E33: =D36 -> 1361.0969 | F33: =E36 -> 1555.7723 | G33: =F36 -> 1587.8097 | H33: =G36 -> 1519.6931 | I33: =H36 -> 1388.6965 | J33: =I36 -> 1216.9496 | K33: =J36 -> 1017.4753 | ... AA33: =Z36 -> 0
B34: Taxable after loss set-off | C34: =C32-C33 -> -899.31259 | D34: =D32-D33 -> -1361.0969 | E34: =E32-E33 -> -1555.7723 | F34: =F32-F33 -> -1587.8097 | G34: =G32-G33 -> -1519.6931 | H34: =H32-H33 -> -1388.6965 | I34: =I32-I33 -> -1216.9496 | J34: =J32-J33 -> -1017.4753 | ... AA34: =AA32-AA33 -> 321.26155
B35: Tax payable | C35: =MAX(0,C34)*Assumptions!$C$83 -> 0 | D35: =MAX(0,D34)*Assumptions!$C$83 -> 0 | E35: =MAX(0,E34)*Assumptions!$C$83 -> 0 | F35: =MAX(0,F34)*Assumptions!$C$83 -> 0 | G35: =MAX(0,G34)*Assumptions!$C$83 -> 0 | H35: =MAX(0,H34)*Assumptions!$C$83 -> 0 | I35: =MAX(0,I34)*Assumptions!$C$83 -> 0 | J35: =MAX(0,J34)*Assumptions!$C$83 -> 0 | ... AA35: =MAX(0,AA34)*Assumptions!$C$83 -> 80.855108
B36: Loss carried forward | C36: =MAX(0,-C34) -> 899.31259 | D36: =MAX(0,-D34) -> 1361.0969 | E36: =MAX(0,-E34) -> 1555.7723 | F36: =MAX(0,-F34) -> 1587.8097 | G36: =MAX(0,-G34) -> 1519.6931 | H36: =MAX(0,-H34) -> 1388.6965 | I36: =MAX(0,-I34) -> 1216.9496 | J36: =MAX(0,-J34) -> 1017.4753 | ... AA36: =MAX(0,-AA34) -> 0
B38: PROFIT & LOSS
B39: Book depreciation (SLM to 5% residual) | C39: =Capex!$C$21*(1-Assumptions!$C$87)/Assumptions!$C$86 -> 109.24977 | D39: =Capex!$C$21*(1-Assumptions!$C$87)/Assumptions!$C$86 -> 109.24977 | E39: =Capex!$C$21*(1-Assumptions!$C$87)/Assumptions!$C$86 -> 109.24977 | F39: =Capex!$C$21*(1-Assumptions!$C$87)/Assumptions!$C$86 -> 109.24977 | G39: =Capex!$C$21*(1-Assumptions!$C$87)/Assumptions!$C$86 -> 109.24977 | H39: =Capex!$C$21*(1-Assumptions!$C$87)/Assumptions!$C$86 -> 109.24977 | I39: =Capex!$C$21*(1-Assumptions!$C$87)/Assumptions!$C$86 -> 109.24977 | J39: =Capex!$C$21*(1-Assumptions!$C$87)/Assumptions!$C$86 -> 109.24977 | ... L39: =Capex!$C$21*(1-Assumptions!$C$87)/Assumptions!$C$86 -> 109.24977 | M39: =Capex!$C$21*(1-Assumptions!$C$87)/Assumptions!$C$86+Capex!$C$28*(1-Assumptions!$C$87)/(25-Assumptions!$C$90+1) -> 134.89977 | N39: =Capex!$C$21*(1-Assumptions!$C$87)/Assumptions!$C$86+Capex!$C$28*(1-Assumptions!$C$87)/(25-Assumptions!$C$90+1) -> 134.89977 | O39: =Capex!$C$21*(1-Assumptions!$C$87)/Assumptions!$C$86+Capex!$C$28*(1-Assumptions!$C$87)/(25-Assumptions!$C$90+1) -> 134.89977 | P39: =Capex!$C$21*(1-Assumptions!$C$87)/Assumptions!$C$86+Capex!$C$28*(1-Assumptions!$C$87)/(25-Assumptions!$C$90+1) -> 134.89977 | Q39: =Capex!$C$21*(1-Assumptions!$C$87)/Assumptions!$C$86+Capex!$C$28*(1-Assumptions!$C$87)/(25-Assumptions!$C$90+1) -> 134.89977 | R39: =Capex!$C$21*(1-Assumptions!$C$87)/Assumptions!$C$86+Capex!$C$28*(1-Assumptions!$C$87)/(25-Assumptions!$C$90+1) -> 134.89977 | S39: =Capex!$C$21*(1-Assumptions!$C$87)/Assumptions!$C$86+Capex!$C$28*(1-Assumptions!$C$87)/(25-Assumptions!$C$90+1) -> 134.89977 | T39: =Capex!$C$21*(1-Assumptions!$C$87)/Assumptions!$C$86+Capex!$C$28*(1-Assumptions!$C$87)/(25-Assumptions!$C$90+1) -> 134.89977 | ... AA39: =Capex!$C$21*(1-Assumptions!$C$87)/Assumptions!$C$86+Capex!$C$28*(1-Assumptions!$C$87)/(25-Assumptions!$C$90+1) -> 134.89977
B40: EBIT | C40: =C23-C39 -> 278.35676 | D40: =D23-D39 -> 276.80463 | E40: =E23-E39 -> 275.18797 | F40: =F23-F39 -> 273.50457 | G40: =G23-G39 -> 271.75211 | H40: =H23-H39 -> 269.92822 | I40: =I23-I39 -> 268.03044 | J40: =J23-J39 -> 266.05624 | ... AA40: =AA23-AA39 -> 192.23755
B41: Interest on term debt | C41: =C47 -> 188.67147 | D41: =D47 -> 186.59012 | E41: =E47 -> 180.06396 | F41: =F47 -> 173.06231 | G41: =G47 -> 165.54753 | H41: =H47 -> 157.47879 | I41: =I47 -> 148.81184 | J41: =J47 -> 139.49871 | ... AA41: =AA47 -> 0
B42: Profit before tax | C42: =C40-C41 -> 89.685288 | D42: =D40-D41 -> 90.214509 | E42: =E40-E41 -> 95.124016 | F42: =F40-F41 -> 100.44225 | G42: =G40-G41 -> 106.20458 | H42: =H40-H41 -> 112.44943 | I42: =I40-I41 -> 119.2186 | J42: =J40-J41 -> 126.55753 | ... AA42: =AA40-AA41 -> 192.23755
B43: PAT | C43: =C42-C35 -> 89.685288 | D43: =D42-D35 -> 90.214509 | E43: =E42-E35 -> 95.124016 | F43: =F42-F35 -> 100.44225 | G43: =G42-G35 -> 106.20458 | H43: =H42-H35 -> 112.44943 | I43: =I42-I35 -> 119.2186 | J43: =J42-J35 -> 126.55753 | ... AA43: =AA42-AA35 -> 111.38245
B45: DEBT SCHEDULE (sculpted, constant DSCR)
B46: Debt — opening | C46: =Capex!$C$22 -> 2156.2454 | D46: =C51 -> 2132.4585 | E46: =D51 -> 2057.8738 | F46: =E51 -> 1977.855 | G46: =F51 -> 1891.9717 | H46: =G51 -> 1799.7575 | I46: =H51 -> 1700.7067 | J46: =I51 -> 1594.271 | K46: =J51 -> 1479.8558 | ... AA46: =Z51 -> 0
B47: Interest | C47: =C46*Assumptions!$C$70 -> 188.67147 | D47: =D46*Assumptions!$C$70 -> 186.59012 | E47: =E46*Assumptions!$C$70 -> 180.06396 | F47: =F46*Assumptions!$C$70 -> 173.06231 | G47: =G46*Assumptions!$C$70 -> 165.54753 | H47: =H46*Assumptions!$C$70 -> 157.47879 | I47: =I46*Assumptions!$C$70 -> 148.81184 | J47: =J46*Assumptions!$C$70 -> 139.49871 | ... AA47: =AA46*Assumptions!$C$70 -> 0
B48: Sculpted debt service target (CFADS/DSCR) | C48: =IF(C2<=Assumptions!$C$71,C55/Assumptions!$C$72,0) -> 212.45835 | D48: =IF(D2<=Assumptions!$C$71,D55/Assumptions!$C$72,0) -> 261.17482 | E48: =IF(E2<=Assumptions!$C$71,E55/Assumptions!$C$72,0) -> 260.08275 | F48: =IF(F2<=Assumptions!$C$71,F55/Assumptions!$C$72,0) -> 258.94556 | G48: =IF(G2<=Assumptions!$C$71,G55/Assumptions!$C$72,0) -> 257.76172 | H48: =IF(H2<=Assumptions!$C$71,H55/Assumptions!$C$72,0) -> 256.52961 | I48: =IF(I2<=Assumptions!$C$71,I55/Assumptions!$C$72,0) -> 255.24757 | J48: =IF(J2<=Assumptions!$C$71,J55/Assumptions!$C$72,0) -> 253.91388 | ... AA48: =IF(AA2<=Assumptions!$C$71,AA55/Assumptions!$C$72,0) -> 0
B49: Principal repayment | C49: =IF(C2=Assumptions!$C$71,C46,MAX(0,MIN(C46,C48-C47))) -> 23.786882 | D49: =IF(D2=Assumptions!$C$71,D46,MAX(0,MIN(D46,D48-D47))) -> 74.584706 | E49: =IF(E2=Assumptions!$C$71,E46,MAX(0,MIN(E46,E48-E47))) -> 80.01879 | F49: =IF(F2=Assumptions!$C$71,F46,MAX(0,MIN(F46,F48-F47))) -> 85.883251 | G49: =IF(G2=Assumptions!$C$71,G46,MAX(0,MIN(G46,G48-G47))) -> 92.214192 | H49: =IF(H2=Assumptions!$C$71,H46,MAX(0,MIN(H46,H48-H47))) -> 99.050822 | I49: =IF(I2=Assumptions!$C$71,I46,MAX(0,MIN(I46,I48-I47))) -> 106.43573 | J49: =IF(J2=Assumptions!$C$71,J46,MAX(0,MIN(J46,J48-J47))) -> 114.41517 | ... AA49: =IF(AA2=Assumptions!$C$71,AA46,MAX(0,MIN(AA46,AA48-AA47))) -> 0
B50: Debt service | C50: =IF(C46>0.000001,C47+C49,0) -> 212.45835 | D50: =IF(D46>0.000001,D47+D49,0) -> 261.17482 | E50: =IF(E46>0.000001,E47+E49,0) -> 260.08275 | F50: =IF(F46>0.000001,F47+F49,0) -> 258.94556 | G50: =IF(G46>0.000001,G47+G49,0) -> 257.76172 | H50: =IF(H46>0.000001,H47+H49,0) -> 256.52961 | I50: =IF(I46>0.000001,I47+I49,0) -> 255.24757 | J50: =IF(J46>0.000001,J47+J49,0) -> 253.91388 | ... AA50: =IF(AA46>0.000001,AA47+AA49,0) -> 0
B51: Debt — closing | C51: =C46-C49 -> 2132.4585 | D51: =D46-D49 -> 2057.8738 | E51: =E46-E49 -> 1977.855 | F51: =F46-F49 -> 1891.9717 | G51: =G46-G49 -> 1799.7575 | H51: =H46-H49 -> 1700.7067 | I51: =I46-I49 -> 1594.271 | J51: =J46-J49 -> 1479.8558 | ... AA51: =AA46-AA49 -> 0
B53: CASH FLOW
B54: Receivables (60 days) / change in WC | C54: =MAX(C13,0)*Assumptions!$C$79/365 -> 73.547614 | D54: =MAX(D13,0)*Assumptions!$C$79/365 -> 73.529724 | E54: =MAX(E13,0)*Assumptions!$C$79/365 -> 73.509505 | F54: =MAX(F13,0)*Assumptions!$C$79/365 -> 73.48688 | G54: =MAX(G13,0)*Assumptions!$C$79/365 -> 73.461771 | H54: =MAX(H13,0)*Assumptions!$C$79/365 -> 73.434098 | I54: =MAX(I13,0)*Assumptions!$C$79/365 -> 73.403778 | J54: =MAX(J13,0)*Assumptions!$C$79/365 -> 73.370726 | ... AA54: =MAX(AA13,0)*Assumptions!$C$79/365 -> 72.297512
B55: CFADS (EBITDA - tax - change in WC) | C55: =C23-C35-C54 -> 314.05891 | D55: =D23-D35-(D54-C54) -> 386.07228 | E55: =E23-E35-(E54-D54) -> 384.45796 | F55: =F23-F35-(F54-E54) -> 382.77696 | G55: =G23-G35-(G54-F54) -> 381.02698 | H55: =H23-H35-(H54-G54) -> 379.20566 | I55: =I23-I35-(I54-H54) -> 377.31053 | J55: =J23-J35-(J54-I54) -> 375.33906 | K55: =K23-K35-(K54-J54) -> 373.28863 | ... AA55: =AA23-AA35-(AA54-Z54) -> 246.37697
B56: BESS augmentation capex | C56: =IF(C2=Assumptions!$C$90,Capex!$C$28,0) -> 0 | D56: =IF(D2=Assumptions!$C$90,Capex!$C$28,0) -> 0 | E56: =IF(E2=Assumptions!$C$90,Capex!$C$28,0) -> 0 | F56: =IF(F2=Assumptions!$C$90,Capex!$C$28,0) -> 0 | G56: =IF(G2=Assumptions!$C$90,Capex!$C$28,0) -> 0 | H56: =IF(H2=Assumptions!$C$90,Capex!$C$28,0) -> 0 | I56: =IF(I2=Assumptions!$C$90,Capex!$C$28,0) -> 0 | J56: =IF(J2=Assumptions!$C$90,Capex!$C$28,0) -> 0 | ... AA56: =IF(AA2=Assumptions!$C$90,Capex!$C$28,0) -> 0
B57: FCFE (CFADS - debt service - augmentation) | C57: =C55-C50-C56 -> 101.60056 | D57: =D55-D50-D56 -> 124.89746 | E57: =E55-E50-E56 -> 124.37521 | F57: =F55-F50-F56 -> 123.83139 | G57: =G55-G50-G56 -> 123.26526 | H57: =H55-H50-H56 -> 122.67605 | I57: =I55-I50-I56 -> 122.06296 | J57: =J55-J50-J56 -> 121.42517 | ... AA57: =AA55-AA50-AA56 -> 246.37697
B58: DSCR (x) | C58: =IF(C50>0.000001,C55/C50,"") -> 1.478214 | D58: =IF(D50>0.000001,D55/D50,"") -> 1.478214 | E58: =IF(E50>0.000001,E55/E50,"") -> 1.478214 | F58: =IF(F50>0.000001,F55/F50,"") -> 1.478214 | G58: =IF(G50>0.000001,G55/G50,"") -> 1.478214 | H58: =IF(H50>0.000001,H55/H50,"") -> 1.478214 | I58: =IF(I50>0.000001,I55/I50,"") -> 1.478214 | J58: =IF(J50>0.000001,J55/J50,"") -> 1.478214 | ... AA58: =IF(AA50>0.000001,AA55/AA50,"")
B59: Post-augmentation DSCR (x) | C59: =IF(C50>0.000001,(C55-C56)/C50,"") -> 1.478214 | D59: =IF(D50>0.000001,(D55-D56)/D50,"") -> 1.478214 | E59: =IF(E50>0.000001,(E55-E56)/E50,"") -> 1.478214 | F59: =IF(F50>0.000001,(F55-F56)/F50,"") -> 1.478214 | G59: =IF(G50>0.000001,(G55-G56)/G50,"") -> 1.478214 | H59: =IF(H50>0.000001,(H55-H56)/H50,"") -> 1.478214 | I59: =IF(I50>0.000001,(I55-I56)/I50,"") -> 1.478214 | J59: =IF(J50>0.000001,(J55-J56)/J50,"") -> 1.478214 | ... AA59: =IF(AA50>0.000001,(AA55-AA56)/AA50,"")
B61: EQUITY & PROJECT CASH FLOWS (t0, t1 = construction years)
B62: Equity cash flow | C62: =-Capex!$C$23*Assumptions!$C$74 -> -323.4368 | D62: =-Capex!$C$23*Assumptions!$C$75 -> -395.31165 | E62: =C57 -> 101.60056 | F62: =D57 -> 124.89746 | G62: =E57 -> 124.37521 | H62: =F57 -> 123.83139 | I62: =G57 -> 123.26526 | J62: =H57 -> 122.67605 | K62: =I57 -> 122.06296 | L62: =J57 -> 121.42517 | ... AC62: =AA57 -> 246.37697
B63: Project cash flow | C63: =-Capex!$C$21*Assumptions!$C$74 -> -1293.7472 | D63: =-Capex!$C$21*Assumptions!$C$75 -> -1581.2466 | E63: =C55-C56 -> 314.05891 | F63: =D55-D56 -> 386.07228 | G63: =E55-E56 -> 384.45796 | H63: =F55-F56 -> 382.77696 | I63: =G55-G56 -> 381.02698 | J63: =H55-H56 -> 379.20566 | K63: =I55-I56 -> 377.31053 | L63: =J55-J56 -> 375.33906 | ... AC63: =AA55-AA56 -> 246.37697
B65: RESULTS
B66: Bid tariff (Rs/kWh) | C66: =Assumptions!$C$16 -> 5.9113
B67: Project IRR (pre-financing, post-tax) | C67: =IRR(C63:AC63) -> 0.10096057
B68: EQUITY IRR | C68: =IRR(C62:AC62) -> 0.14000086
B69: Equity NPV @ discount rate | C69: =C62+NPV(Assumptions!$C$78,D62:AC62) -> 257.39698
B70: Min DSCR (debt years) | C70: =MIN(C58:AA58) -> 1.4782077
B71: Average DSCR (debt years) | C71: =AVERAGE(C58:AA58) -> 1.4782136
B72: IRR target met (>= 14%)? | C72: =IF(C68>=Assumptions!$C$76-0.0001,"PASS","FAIL") -> PASS
B73: DSCR floor met (>= 1.10x)? | C73: =IF(C70>=Assumptions!$C$77,"PASS","FAIL") -> PASS
B74: Bid tariff is the LOWEST tariff meeting both -> re-derive with Goal Seek (see Assumptions legend).

Sheet Tender Compliance
B1: Hard Tender Conditions & Optimized Output Validation
B3: HARD TENDER CONDITIONS (NHPC FDRE T-II) | C3: Model value | D3: Requirement | E3: Status | F3: Reference
B4: Monthly peak availability — minimum month (year 1) | C4: ='Monthly Y1'!F16 -> 0.9 | D4: =Assumptions!$C$24 -> 0.9 | E4: =IF('Monthly Y1'!F16>=Assumptions!$C$24,"PASS","FAIL") -> PASS | F4: RfS: 90% of contracted capacity across 4 daily peak hours, tested monthly
B5: All 12 months compliant (year 1) | C5: ='Monthly Y1'!K16 -> ALL PASS | D5: "ALL PASS" | E5: =IF('Monthly Y1'!K16="ALL PASS","PASS","FAIL") -> PASS | F5: Both peak and annual LDs can apply in the same year
B6: Annual CUF — minimum year | C6: =MIN('Dispatch 25Y'!I4:I28) -> 0.4 | D6: =Assumptions!$C$19*(1-Assumptions!$C$20) -> 0.34 | E6: =IF(MIN('Dispatch 25Y'!I4:I28)>=Assumptions!$C$19*(1-Assumptions!$C$20),"PASS","FAIL") -> PASS | F6: Floor: declared CUF - 15% (34%)
B7: Annual CUF — maximum year (offtake cap) | C7: =MAX('Dispatch 25Y'!I4:I28) -> 0.4 | D7: =Assumptions!$C$19*Assumptions!$C$21 -> 0.44 | E7: =IF(MAX('Dispatch 25Y'!I4:I28)<=Assumptions!$C$19*Assumptions!$C$21+0.0000001,"PASS","FAIL") -> PASS | F7: Cap: 110% of declared CUF (44%) — NHPC purchase limit
B8: Liquidated damages — total (year 1) | C8: ='Monthly Y1'!J16 -> 0 | D8: 0 | E8: =IF('Monthly Y1'!J16<=0.000001,"PASS","FAIL") -> PASS | F8: 1.5x tariff on shortfall energy
B9: Bid capacity >= minimum project size | C9: =Assumptions!$C$15 -> 200 | D9: 50 MW | E9: =IF(Assumptions!$C$15>=50,"PASS","FAIL") -> PASS | F9: RfS minimum 50 MW
B10: Bid capacity multiple of 10 MW | C10: =MOD(Assumptions!$C$15,10) -> 0 | D10: 0 | E10: =IF(MOD(Assumptions!$C$15,10)=0,"PASS","FAIL") -> PASS
B11: Bid capacity <= bidder cap | C11: =Assumptions!$C$15 -> 200 | D11: 600 MW | E11: =IF(Assumptions!$C$15<=600,"PASS","FAIL") -> PASS | F11: RfS maximum 600 MW per bidder
B12: BESS charging source | C12: "RE only" | D12: "RE only" | E12: "PASS" | F12: By construction: BESS charges only from co-located RE (no grid/fossil)
B13: Declared CUF >= 40% | C13: =Assumptions!$C$19 -> 0.4 | D13: 40% | E13: =IF(Assumptions!$C$19>=0.4,"PASS","FAIL") -> PASS | F13: RfS minimum declaration
B15: OPTIMIZED OUTPUT VALIDATION (model vs optimizer result) | C15: Optimizer | D15: This model | E15: Match
B16: Solar capacity (MW) | C16: 288.8 | D16: =Assumptions!$C$11 -> 288.8 | E16: =IF(ABS(C16-D16)<0.005,"MATCH","DIFF") -> MATCH
B17: Wind capacity (MW) | C17: 40.9 | D17: =Assumptions!$C$12 -> 40.9 | E17: =IF(ABS(C17-D17)<0.005,"MATCH","DIFF") -> MATCH
B18: BESS power (MW) | C18: 180 | D18: =Assumptions!$C$13 -> 180 | E18: =IF(ABS(C18-D18)<0.005,"MATCH","DIFF") -> MATCH
B19: BESS energy (MWh) | C19: 540 | D19: =Assumptions!$C$14 -> 540 | E19: =IF(ABS(C19-D19)<0.005,"MATCH","DIFF") -> MATCH
B20: Selected bid capacity (MW) | C20: 200 | D20: =Assumptions!$C$15 -> 200 | E20: =IF(ABS(C20-D20)<0.005,"MATCH","DIFF") -> MATCH
B21: Required tariff (Rs/kWh) — declared CUF 40% / 90% availability | C21: 5.9113 | D21: =Assumptions!$C$16 -> 5.9113 | E21: =IF(ABS(C21-D21)<0.005,"MATCH","DIFF") -> MATCH
B22: Equity IRR at bid tariff | C22: 0.14 | D22: ='Financial Model'!C68 -> 0.14000086 | E22: =IF(ABS(C22-D22)<0.001,"MATCH","DIFF") -> MATCH
B23: Min DSCR at bid tariff (>= floor) | C23: 1.1 | D23: ='Financial Model'!C70 -> 1.4782077 | E23: =IF(D23>=C23,"PASS","FAIL") -> PASS

Sheet Validation
B1: Validation — Excel formulas vs dispatch engine (calibrated reference run)
B2: Engine: fdre_enterprise_engine.py, seed 42, capacities as bid, delivery at declared CUF 40% / availability 90% (compliant, zero LD), tariff Rs 5.9113.
B4: Metric | C4: Engine | D4: This model | E4: Delta % | F4: Status
B5: Hard capex (cr) | C5: 2705.6081 | D5: =Capex!C15 -> 2705.6081 | E5: =IF(ABS(C5)>0.0001,(D5-C5)/ABS(C5),D5-C5) -> 0 | F5: =IF(ABS(E5)<0.005,"PASS","CHECK") -> PASS
B6: IDC (cr) | C6: 169.3857 | D6: =Capex!C20 -> 169.3857 | E6: =IF(ABS(C6)>0.0001,(D6-C6)/ABS(C6),D6-C6) -> -1.3303488e-09 | F6: =IF(ABS(E6)<0.005,"PASS","CHECK") -> PASS
B7: Total project cost (cr) | C7: 2874.9938 | D7: =Capex!C21 -> 2874.9938 | E7: =IF(ABS(C7)>0.0001,(D7-C7)/ABS(C7),D7-C7) -> -7.8380105e-11 | F7: =IF(ABS(E7)<0.005,"PASS","CHECK") -> PASS
B8: Debt (cr) | C8: 2156.2454 | D8: =Capex!C22 -> 2156.2454 | E8: =IF(ABS(C8)>0.0001,(D8-C8)/ABS(C8),D8-C8) -> 1.5350448e-10 | F8: =IF(ABS(E8)<0.005,"PASS","CHECK") -> PASS
B9: Equity (cr) | C9: 718.74846 | D9: =Capex!C23 -> 718.74846 | E9: =IF(ABS(C9)>0.0001,(D9-C9)/ABS(C9),D9-C9) -> 6.1727317e-10 | F9: =IF(ABS(E9)<0.005,"PASS","CHECK") -> PASS
B10: EMD (cr) | C10: 10 | D10: =Capex!C25 -> 10 | E10: =IF(ABS(C10)>0.0001,(D10-C10)/ABS(C10),D10-C10) -> 0 | F10: =IF(ABS(E10)<0.005,"PASS","CHECK") -> PASS
B11: PBG (cr) | C11: 145.806 | D11: =Capex!C26 -> 145.806 | E11: =IF(ABS(C11)>0.0001,(D11-C11)/ABS(C11),D11-C11) -> 0 | F11: =IF(ABS(E11)<0.005,"PASS","CHECK") -> PASS
B12: Year-1 PPA energy (MWh) | C12: 701280 | D12: ='Dispatch 25Y'!H4 -> 701280 | E12: =IF(ABS(C12)>0.0001,(D12-C12)/ABS(C12),D12-C12) -> 0 | F12: =IF(ABS(E12)<0.005,"PASS","CHECK") -> PASS
B13: Year-1 merchant energy (MWh) | C13: 105444.81 | D13: ='Dispatch 25Y'!K4 -> 105444.81 | E13: =IF(ABS(C13)>0.0001,(D13-C13)/ABS(C13),D13-C13) -> -2.438135e-12 | F13: =IF(ABS(E13)<0.005,"PASS","CHECK") -> PASS
B14: Year-1 total revenue (cr) | C14: 447.41465 | D14: ='Financial Model'!C13 -> 447.41465 | E14: =IF(ABS(C14)>0.0001,(D14-C14)/ABS(C14),D14-C14) -> -5.1514523e-10 | F14: =IF(ABS(E14)<0.005,"PASS","CHECK") -> PASS
B15: Year-1 total opex (cr) | C15: 59.808127 | D15: ='Financial Model'!C22 -> 59.808127 | E15: =IF(ABS(C15)>0.0001,(D15-C15)/ABS(C15),D15-C15) -> 2.5041837e-09 | F15: =IF(ABS(E15)<0.005,"PASS","CHECK") -> PASS
B16: Year-1 EBITDA (cr) | C16: 387.60652 | D16: ='Financial Model'!C23 -> 387.60652 | E16: =IF(ABS(C16)>0.0001,(D16-C16)/ABS(C16),D16-C16) -> -9.8103109e-10 | F16: =IF(ABS(E16)<0.005,"PASS","CHECK") -> PASS
B17: Year-1 CFADS (cr) | C17: 314.05891 | D17: ='Financial Model'!C55 -> 314.05891 | E17: =IF(ABS(C17)>0.0001,(D17-C17)/ABS(C17),D17-C17) -> -1.3053778e-10 | F17: =IF(ABS(E17)<0.005,"PASS","CHECK") -> PASS
B18: Year-1 FCFE (cr) | C18: 101.60054 | D18: ='Financial Model'!C57 -> 101.60056 | E18: =IF(ABS(C18)>0.0001,(D18-C18)/ABS(C18),D18-C18) -> 1.8597823e-07 | F18: =IF(ABS(E18)<0.005,"PASS","CHECK") -> PASS
B19: Year-14 tax (first tax-paying year, cr) | C19: 44.565529 | D19: ='Financial Model'!P35 -> 44.565463 | E19: =IF(ABS(C19)>0.0001,(D19-C19)/ABS(C19),D19-C19) -> -1.4803761e-06 | F19: =IF(ABS(E19)<0.005,"PASS","CHECK") -> PASS
B20: Year-11 augmentation (cr) | C20: 405 | D20: ='Financial Model'!M56 -> 405 | E20: =IF(ABS(C20)>0.0001,(D20-C20)/ABS(C20),D20-C20) -> 0 | F20: =IF(ABS(E20)<0.005,"PASS","CHECK") -> PASS
B21: Year-25 EBITDA (cr) | C21: 327.13732 | D21: ='Financial Model'!AA23 -> 327.13732 | E21: =IF(ABS(C21)>0.0001,(D21-C21)/ABS(C21),D21-C21) -> 2.5524458e-10 | F21: =IF(ABS(E21)<0.005,"PASS","CHECK") -> PASS
B22: Equity IRR | C22: 0.140001 | D22: ='Financial Model'!C68 -> 0.14000086 | E22: =IF(ABS(C22)>0.0001,(D22-C22)/ABS(C22),D22-C22) -> -9.9993313e-07 | F22: =IF(ABS(E22)<0.005,"PASS","CHECK") -> PASS
B23: Project IRR | C23: 0.100961 | D23: ='Financial Model'!C67 -> 0.10096057 | E23: =IF(ABS(C23)>0.0001,(D23-C23)/ABS(C23),D23-C23) -> -4.3048429e-06 | F23: =IF(ABS(E23)<0.005,"PASS","CHECK") -> PASS
B24: Min DSCR (x) | C24: 1.478214 | D24: ='Financial Model'!C70 -> 1.4782077 | E24: =IF(ABS(C24)>0.0001,(D24-C24)/ABS(C24),D24-C24) -> -4.2765995e-06 | F24: =IF(ABS(E24)<0.005,"PASS","CHECK") -> PASS
B25: Equity NPV @10% (cr) | C25: 257.39693 | D25: ='Financial Model'!C69 -> 257.39698 | E25: =IF(ABS(C25)>0.0001,(D25-C25)/ABS(C25),D25-C25) -> 1.7360921e-07 | F25: =IF(ABS(E25)<0.005,"PASS","CHECK") -> PASS
B27: PASS = within 0.5%. Engine values are hardcoded reference outputs from the calibrated run; model values are live formulas.

Sheet Profiles 8760
A1: Hourly capacity-factor profiles (engine seed 42, measured-yield calibrated x1.1911, mean-preserving clip). Values.
A2: Hour | B2: Month | C2: Day | D2: HourOfDay | E2: PeakFlag | F2: SolarCF | G2: WindCF | H2: RemPeakOblMWh
A3: 1 | B3: 1 | C3: 1 | D3: 0 | E3: 0 | F3: 0 | G3: 0.209117 | H3: 292000
A4: 2 | B4: 1 | C4: 1 | D4: 1 | E4: 0 | F4: 0 | G4: 0.257582 | H4: 292000
A5: 3 | B5: 1 | C5: 1 | D5: 2 | E5: 0 | F5: 0 | G5: 0.274103 | H5: 292000
A6: 4 | B6: 1 | C6: 1 | D6: 3 | E6: 0 | F6: 0 | G6: 0.368831 | H6: 292000
A7: 5 | B7: 1 | C7: 1 | D7: 4 | E7: 0 | F7: 0 | G7: 0.292277 | H7: 292000
A8: 6 | B8: 1 | C8: 1 | D8: 5 | E8: 0 | F8: 0 | G8: 0.193604 | H8: 292000
A9: 7 | B9: 1 | C9: 1 | D9: 6 | E9: 0 | F9: 0 | G9: 0.157591 | H9: 292000
A10: 8 | B10: 1 | C10: 1 | D10: 7 | E10: 1 | F10: 0.06852 | G10: 0.20751 | H10: 291800
A11: 9 | B11: 1 | C11: 1 | D11: 8 | E11: 1 | F11: 0.359201 | G11: 0.347475 | H11: 291600
A12: 10 | B12: 1 | C12: 1 | D12: 9 | E12: 0 | F12: 0.690594 | G12: 0.291436 | H12: 291600
A13: 11 | B13: 1 | C13: 1 | D13: 10 | E13: 0 | F13: 0.983899 | G13: 0.305138 | H13: 291600
A14: 12 | B14: 1 | C14: 1 | D14: 11 | E14: 0 | F14: 1 | G14: 0.306961 | H14: 291600
... A8762: 8760 | B8762: 12 | C8762: 365 | D8762: 23 | E8762: 0 | F8762: 0 | G8762: 0.857641 | H8762: 0

Sheet 25Y Hourly Validation
B1: 25-Year Exact Hourly Validation — engine full-term dispatch (8,760 h/yr, degradation + BESS ageing + year-11 augmentation)
B2: Engine exact mode, measured-yield calibrated profiles, green support enabled (RfS 5% allowance). Values in cols C–J; checks are formulas.
B4: Year | C4: Usable BESS MWh | D4: RTE | E4: Solar deg factor | F4: Wind deg factor | G4: PPA MWh (project) | H4: PPA CUF | I4: CUF in band? | J4: Min month avail (delivered) | K4: Green MWh | L4: Green % annual | M4: Green <= 5%? | N4: Avail incl. green | O4: Avail >= 90%?
B5: 1 | C5: 510.81 | D5: 0.8668 | E5: =(1-Assumptions!$C$35)^(B5-1) -> 1 | F5: =(1-Assumptions!$C$36)^(B5-1) -> 1 | G5: 771408 | H5: =G5/(Assumptions!$C$15*Assumptions!$C$23) -> 0.44 | I5: =IF(AND(H5>=Assumptions!$C$19*(1-Assumptions!$C$20),H5<=Assumptions!$C$19*Assumptions!$C$21+0.000001),"PASS","FAIL") -> PASS | J5: 0.8241 | K5: 4556.8 | L5: =K5/G5 -> 0.0059071205 | M5: =IF(L5<=0.05+0.000001,"PASS","FAIL") -> PASS | N5: 0.9 | O5: =IF(N5>=Assumptions!$C$24-0.000001,"PASS","FAIL") -> PASS
B6: 2 | C6: 488.59 | D6: 0.8668 | E6: =(1-Assumptions!$C$35)^(B6-1) -> 0.995 | F6: =(1-Assumptions!$C$36)^(B6-1) -> 0.998 | G6: 771408 | H6: =G6/(Assumptions!$C$15*Assumptions!$C$23) -> 0.44 | I6: =IF(AND(H6>=Assumptions!$C$19*(1-Assumptions!$C$20),H6<=Assumptions!$C$19*Assumptions!$C$21+0.000001),"PASS","FAIL") -> PASS | J6: 0.796 | K6: 7332.6 | L6: =K6/G6 -> 0.0095054757 | M6: =IF(L6<=0.05+0.000001,"PASS","FAIL") -> PASS | N6: 0.9 | O6: =IF(N6>=Assumptions!$C$24-0.000001,"PASS","FAIL") -> PASS
B7: 3 | C7: 477.2 | D7: 0.8612 | E7: =(1-Assumptions!$C$35)^(B7-1) -> 0.990025 | F7: =(1-Assumptions!$C$36)^(B7-1) -> 0.996004 | G7: 771408 | H7: =G7/(Assumptions!$C$15*Assumptions!$C$23) -> 0.44 | I7: =IF(AND(H7>=Assumptions!$C$19*(1-Assumptions!$C$20),H7<=Assumptions!$C$19*Assumptions!$C$21+0.000001),"PASS","FAIL") -> PASS | J7: 0.7812 | K7: 9176.1 | L7: =K7/G7 -> 0.011895262 | M7: =IF(L7<=0.05+0.000001,"PASS","FAIL") -> PASS | N7: 0.9 | O7: =IF(N7>=Assumptions!$C$24-0.000001,"PASS","FAIL") -> PASS
B8: 4 | C8: 467.45 | D8: 0.8612 | E8: =(1-Assumptions!$C$35)^(B8-1) -> 0.98507488 | F8: =(1-Assumptions!$C$36)^(B8-1) -> 0.99401199 | G8: 771408 | H8: =G8/(Assumptions!$C$15*Assumptions!$C$23) -> 0.44 | I8: =IF(AND(H8>=Assumptions!$C$19*(1-Assumptions!$C$20),H8<=Assumptions!$C$19*Assumptions!$C$21+0.000001),"PASS","FAIL") -> PASS | J8: 0.7684 | K8: 10764.5 | L8: =K8/G8 -> 0.013954354 | M8: =IF(L8<=0.05+0.000001,"PASS","FAIL") -> PASS | N8: 0.9 | O8: =IF(N8>=Assumptions!$C$24-0.000001,"PASS","FAIL") -> PASS
B9: 5 | C9: 458.71 | D9: 0.8612 | E9: =(1-Assumptions!$C$35)^(B9-1) -> 0.9801495 | F9: =(1-Assumptions!$C$36)^(B9-1) -> 0.99202397 | G9: 771408 | H9: =G9/(Assumptions!$C$15*Assumptions!$C$23) -> 0.44 | I9: =IF(AND(H9>=Assumptions!$C$19*(1-Assumptions!$C$20),H9<=Assumptions!$C$19*Assumptions!$C$21+0.000001),"PASS","FAIL") -> PASS | J9: 0.7568 | K9: 12476.7 | L9: =K9/G9 -> 0.016173931 | M9: =IF(L9<=0.05+0.000001,"PASS","FAIL") -> PASS | N9: 0.9 | O9: =IF(N9>=Assumptions!$C$24-0.000001,"PASS","FAIL") -> PASS
B10: 6 | C10: 450.57 | D10: 0.8612 | E10: =(1-Assumptions!$C$35)^(B10-1) -> 0.97524875 | F10: =(1-Assumptions!$C$36)^(B10-1) -> 0.99003992 | G10: 771408 | H10: =G10/(Assumptions!$C$15*Assumptions!$C$23) -> 0.44 | I10: =IF(AND(H10>=Assumptions!$C$19*(1-Assumptions!$C$20),H10<=Assumptions!$C$19*Assumptions!$C$21+0.000001),"PASS","FAIL") -> PASS | J10: 0.746 | K10: 14091.8 | L10: =K10/G10 -> 0.018267635 | M10: =IF(L10<=0.05+0.000001,"PASS","FAIL") -> PASS | N10: 0.9 | O10: =IF(N10>=Assumptions!$C$24-0.000001,"PASS","FAIL") -> PASS
B11: 7 | C11: 443.03 | D11: 0.8557 | E11: =(1-Assumptions!$C$35)^(B11-1) -> 0.97037251 | F11: =(1-Assumptions!$C$36)^(B11-1) -> 0.98805984 | G11: 771408 | H11: =G11/(Assumptions!$C$15*Assumptions!$C$23) -> 0.44 | I11: =IF(AND(H11>=Assumptions!$C$19*(1-Assumptions!$C$20),H11<=Assumptions!$C$19*Assumptions!$C$21+0.000001),"PASS","FAIL") -> PASS | J11: 0.736 | K11: 15703.1 | L11: =K11/G11 -> 0.020356413 | M11: =IF(L11<=0.05+0.000001,"PASS","FAIL") -> PASS | N11: 0.9 | O11: =IF(N11>=Assumptions!$C$24-0.000001,"PASS","FAIL") -> PASS
B12: 8 | C12: 435.88 | D12: 0.8557 | E12: =(1-Assumptions!$C$35)^(B12-1) -> 0.96552065 | F12: =(1-Assumptions!$C$36)^(B12-1) -> 0.98608372 | G12: 771408 | H12: =G12/(Assumptions!$C$15*Assumptions!$C$23) -> 0.44 | I12: =IF(AND(H12>=Assumptions!$C$19*(1-Assumptions!$C$20),H12<=Assumptions!$C$19*Assumptions!$C$21+0.000001),"PASS","FAIL") -> PASS | J12: 0.7264 | K12: 17471.6 | L12: =K12/G12 -> 0.022648974 | M12: =IF(L12<=0.05+0.000001,"PASS","FAIL") -> PASS | N12: 0.9 | O12: =IF(N12>=Assumptions!$C$24-0.000001,"PASS","FAIL") -> PASS
B13: 9 | C13: 429.08 | D13: 0.8557 | E13: =(1-Assumptions!$C$35)^(B13-1) -> 0.96069304 | F13: =(1-Assumptions!$C$36)^(B13-1) -> 0.98411155 | G13: 771408 | H13: =G13/(Assumptions!$C$15*Assumptions!$C$23) -> 0.44 | I13: =IF(AND(H13>=Assumptions!$C$19*(1-Assumptions!$C$20),H13<=Assumptions!$C$19*Assumptions!$C$21+0.000001),"PASS","FAIL") -> PASS | J13: 0.7172 | K13: 19328.6 | L13: =K13/G13 -> 0.025056261 | M13: =IF(L13<=0.05+0.000001,"PASS","FAIL") -> PASS | N13: 0.9 | O13: =IF(N13>=Assumptions!$C$24-0.000001,"PASS","FAIL") -> PASS
B14: 10 | C14: 422.54 | D14: 0.8557 | E14: =(1-Assumptions!$C$35)^(B14-1) -> 0.95588958 | F14: =(1-Assumptions!$C$36)^(B14-1) -> 0.98214333 | G14: 771408 | H14: =G14/(Assumptions!$C$15*Assumptions!$C$23) -> 0.44 | I14: =IF(AND(H14>=Assumptions!$C$19*(1-Assumptions!$C$20),H14<=Assumptions!$C$19*Assumptions!$C$21+0.000001),"PASS","FAIL") -> PASS | J14: 0.7084 | K14: 21204.5 | L14: =K14/G14 -> 0.027488048 | M14: =IF(L14<=0.05+0.000001,"PASS","FAIL") -> PASS | N14: 0.9 | O14: =IF(N14>=Assumptions!$C$24-0.000001,"PASS","FAIL") -> PASS
B15: 11 | C15: 510.81 | D15: 0.8668 | E15: =(1-Assumptions!$C$35)^(B15-1) -> 0.95111013 | F15: =(1-Assumptions!$C$36)^(B15-1) -> 0.98017904 | G15: 771408 | H15: =G15/(Assumptions!$C$15*Assumptions!$C$23) -> 0.44 | I15: =IF(AND(H15>=Assumptions!$C$19*(1-Assumptions!$C$20),H15<=Assumptions!$C$19*Assumptions!$C$21+0.000001),"PASS","FAIL") -> PASS | J15: 0.8157 | K15: 5611.8 | L15: =K15/G15 -> 0.0072747495 | M15: =IF(L15<=0.05+0.000001,"PASS","FAIL") -> PASS | N15: 0.9 | O15: =IF(N15>=Assumptions!$C$24-0.000001,"PASS","FAIL") -> PASS
B16: 12 | C16: 488.59 | D16: 0.8668 | E16: =(1-Assumptions!$C$35)^(B16-1) -> 0.94635458 | F16: =(1-Assumptions!$C$36)^(B16-1) -> 0.97821869 | G16: 771408 | H16: =G16/(Assumptions!$C$15*Assumptions!$C$23) -> 0.44 | I16: =IF(AND(H16>=Assumptions!$C$19*(1-Assumptions!$C$20),H16<=Assumptions!$C$19*Assumptions!$C$21+0.000001),"PASS","FAIL") -> PASS | J16: 0.7877 | K16: 8680 | L16: =K16/G16 -> 0.011252152 | M16: =IF(L16<=0.05+0.000001,"PASS","FAIL") -> PASS | N16: 0.9 | O16: =IF(N16>=Assumptions!$C$24-0.000001,"PASS","FAIL") -> PASS
... B29: 25 | C29: 422.54 | D29: 0.8557 | E29: =(1-Assumptions!$C$35)^(B29-1) -> 0.88665351 | F29: =(1-Assumptions!$C$36)^(B29-1) -> 0.95308798 | G29: 760767.2 | H29: =G29/(Assumptions!$C$15*Assumptions!$C$23) -> 0.43393064 | I29: =IF(AND(H29>=Assumptions!$C$19*(1-Assumptions!$C$20),H29<=Assumptions!$C$19*Assumptions!$C$21+0.000001),"PASS","FAIL") -> PASS | J29: 0.6961 | K29: 24915 | L29: =K29/G29 -> 0.032749835 | M29: =IF(L29<=0.05+0.000001,"PASS","FAIL") -> PASS | N29: 0.9 | O29: =IF(N29>=Assumptions!$C$24-0.000001,"PASS","FAIL") -> PASS
B30: ALL YEARS | I30: =IF(COUNTIF(I5:I29,"FAIL")=0,"PASS — CUF within +10%/-15% band, 25/25 years","FAIL") -> PASS — CUF within +10%/-15% band, 25/25 years
I31: =IF(COUNTIF(O5:O29,"FAIL")=0,"PASS — availability >= 90%, 300/300 months","FAIL") -> PASS — availability >= 90%, 300/300 months
I32: =IF(COUNTIF(M5:M29,"FAIL")=0,"PASS — green support within 5% allowance","FAIL") -> PASS — green support within 5% allowance
B33: Reconciliation: the project physically delivers PPA energy at the +10% offtake cap (44% CUF) with peak availability held at the 90% floor via green
B34: support (max 3.2% of annual vs 5% allowed). The Financial Model conservatively bills at the declared 40% CUF (offtake lever = 1.00); set the lever
B35: to 1.10 to price full-cap offtake. Availability incl. green = engine result after allocating green to monthly peak shortfalls (fills exactly to floor).
B37: Monthly peak availability delivered by the project (before green support) — engine hourly results
B38: Year | C38: Jan | D38: Feb | E38: Mar | F38: Apr | G38: May | H38: Jun | I38: Jul | J38: Aug | K38: Sep | L38: Oct | M38: Nov | N38: Dec | O38: Min
B39: 1 | C39: 0.8241 | D39: 0.8886 | E39: 0.9712 | F39: 0.9821 | G39: 0.9887 | H39: 0.99 | I39: 0.9871 | J39: 0.9796 | K39: 0.9531 | L39: 0.9283 | M39: 0.8655 | N39: 0.8358 | O39: =MIN(C39:N39) -> 0.8241
B40: 2 | C40: 0.796 | D40: 0.8602 | E40: 0.9548 | F40: 0.9817 | G40: 0.9886 | H40: 0.9892 | I40: 0.9773 | J40: 0.9646 | K40: 0.929 | L40: 0.8998 | M40: 0.8351 | N40: 0.8072 | O40: =MIN(C40:N40) -> 0.796
B41: 3 | C41: 0.7812 | D41: 0.8451 | E41: 0.9419 | F41: 0.9805 | G41: 0.9886 | H41: 0.9865 | I41: 0.9676 | J41: 0.9525 | K41: 0.9139 | L41: 0.8846 | M41: 0.8189 | N41: 0.7922 | O41: =MIN(C41:N41) -> 0.7812
B42: 4 | C42: 0.7684 | D42: 0.832 | E42: 0.9293 | F42: 0.9784 | G42: 0.9886 | H42: 0.9829 | I42: 0.9565 | J42: 0.9406 | K42: 0.9006 | L42: 0.8714 | M42: 0.8052 | N42: 0.7792 | O42: =MIN(C42:N42) -> 0.7684
B43: 5 | C43: 0.7568 | D43: 0.8202 | E43: 0.9176 | F43: 0.9753 | G43: 0.9885 | H43: 0.9781 | I43: 0.9462 | J43: 0.9291 | K43: 0.8886 | L43: 0.8595 | M43: 0.7932 | N43: 0.7672 | O43: =MIN(C43:N43) -> 0.7568
B44: 6 | C44: 0.746 | D44: 0.8091 | E44: 0.9065 | F44: 0.9715 | G44: 0.9885 | H44: 0.9719 | I44: 0.9359 | J44: 0.9178 | K44: 0.8773 | L44: 0.8483 | M44: 0.7823 | N44: 0.7555 | O44: =MIN(C44:N44) -> 0.746
B45: 7 | C45: 0.736 | D45: 0.7987 | E45: 0.8959 | F45: 0.9664 | G45: 0.9882 | H45: 0.9658 | I45: 0.9256 | J45: 0.9072 | K45: 0.8668 | L45: 0.8378 | M45: 0.7721 | N45: 0.7446 | O45: =MIN(C45:N45) -> 0.736
B46: 8 | C46: 0.7264 | D46: 0.7888 | E46: 0.8857 | F46: 0.96 | G46: 0.9877 | H46: 0.9596 | I46: 0.9154 | J46: 0.8971 | K46: 0.8567 | L46: 0.8278 | M46: 0.7624 | N46: 0.734 | O46: =MIN(C46:N46) -> 0.7264
B47: 9 | C47: 0.7172 | D47: 0.7794 | E47: 0.8759 | F47: 0.952 | G47: 0.9865 | H47: 0.9529 | I47: 0.9057 | J47: 0.8875 | K47: 0.8472 | L47: 0.8183 | M47: 0.7531 | N47: 0.7239 | O47: =MIN(C47:N47) -> 0.7172
B48: 10 | C48: 0.7084 | D48: 0.7703 | E48: 0.8664 | F48: 0.9438 | G48: 0.9849 | H48: 0.946 | I48: 0.8962 | J48: 0.8782 | K48: 0.838 | L48: 0.809 | M48: 0.7442 | N48: 0.7147 | O48: =MIN(C48:N48) -> 0.7084
B49: 11 | C49: 0.8157 | D49: 0.8773 | E49: 0.9642 | F49: 0.9818 | G49: 0.9883 | H49: 0.9895 | I49: 0.9826 | J49: 0.9732 | K49: 0.943 | L49: 0.916 | M49: 0.8514 | N49: 0.8256 | O49: =MIN(C49:N49) -> 0.8157
B50: 12 | C50: 0.7877 | D50: 0.849 | E50: 0.9423 | F50: 0.9801 | G50: 0.9883 | H50: 0.9859 | I50: 0.968 | J50: 0.9549 | K50: 0.9164 | L50: 0.8875 | M50: 0.8232 | N50: 0.7952 | O50: =MIN(C50:N50) -> 0.7877
... B63: 25 | C63: 0.6961 | D63: 0.7542 | E63: 0.8448 | F63: 0.9202 | G63: 0.9775 | H63: 0.9242 | I63: 0.8781 | J63: 0.8611 | K63: 0.8199 | L63: 0.7915 | M63: 0.7306 | N63: 0.6968 | O63: =MIN(C63:N63) -> 0.6961

Sheet Hourly Dispatch
A1: HOURLY DISPATCH — formula-driven 8,760-hour dispatch for the SELECTED YEAR, with that year's degradation, BESS state-of-health (incl. year-11 augmentation reset) and RTE.
A2: Single-aggregated-node replica of the engine dispatch (node interconnection limits not modelled per-hour); cross-checked against the engine below. Change B4 to any year 1-25.
A4: SELECTED YEAR | B4: 1 | T4: MONTHLY PEAK COMPLIANCE — selected year
A5: Usable BESS (MWh) | B5: =INDEX('25Y Hourly Validation'!C5:C29,$B$4) -> 510.81 | T5: Month | U5: Obligation MWh | V5: Delivered MWh | W5: Availability | X5: Green to floor MWh | Y5: Avail incl. green | Z5: >=90%?
A6: RTE (year) | B6: =INDEX('25Y Hourly Validation'!D5:D29,$B$4) -> 0.8668 | T6: 1 | U6: =SUMIFS($G$14:$G$8773,$B$14:$B$8773,T6) -> 24800 | V6: =SUMIFS($J$14:$J$8773,$B$14:$B$8773,T6) -> 22819.207 | W6: =V6/U6 -> 0.9201293 | X6: =MAX(0,Assumptions!$C$24*U6-V6) -> 0 | Y6: =(V6+X6)/U6 -> 0.9201293 | Z6: =IF(Y6>=Assumptions!$C$24-0.000001,"PASS","FAIL") -> PASS
A7: Solar degradation factor | B7: =(1-Assumptions!$C$35)^($B$4-1) -> 1 | T7: 2 | U7: =SUMIFS($G$14:$G$8773,$B$14:$B$8773,T7) -> 22400 | V7: =SUMIFS($J$14:$J$8773,$B$14:$B$8773,T7) -> 21524.061 | W7: =V7/U7 -> 0.96089557 | X7: =MAX(0,Assumptions!$C$24*U7-V7) -> 0 | Y7: =(V7+X7)/U7 -> 0.96089557 | Z7: =IF(Y7>=Assumptions!$C$24-0.000001,"PASS","FAIL") -> PASS
A8: Wind degradation factor | B8: =(1-Assumptions!$C$36)^($B$4-1) -> 1 | T8: 3 | U8: =SUMIFS($G$14:$G$8773,$B$14:$B$8773,T8) -> 24800 | V8: =SUMIFS($J$14:$J$8773,$B$14:$B$8773,T8) -> 24357.772 | W8: =V8/U8 -> 0.98216823 | X8: =MAX(0,Assumptions!$C$24*U8-V8) -> 0 | Y8: =(V8+X8)/U8 -> 0.98216823 | Z8: =IF(Y8>=Assumptions!$C$24-0.000001,"PASS","FAIL") -> PASS
A9: Opening SOC (50% usable) | B9: =0.5*$B$5 -> 255.405 | T9: 4 | U9: =SUMIFS($G$14:$G$8773,$B$14:$B$8773,T9) -> 24000 | V9: =SUMIFS($J$14:$J$8773,$B$14:$B$8773,T9) -> 23569.964 | W9: =V9/U9 -> 0.98208184 | X9: =MAX(0,Assumptions!$C$24*U9-V9) -> 0 | Y9: =(V9+X9)/U9 -> 0.98208184 | Z9: =IF(Y9>=Assumptions!$C$24-0.000001,"PASS","FAIL") -> PASS
A10: Annual PPA cap (MWh, 110% x declared) | B10: =Assumptions!$C$19*Assumptions!$C$21*Assumptions!$C$15*Assumptions!$C$23 -> 771408 | T10: 5 | U10: =SUMIFS($G$14:$G$8773,$B$14:$B$8773,T10) -> 24800 | V10: =SUMIFS($J$14:$J$8773,$B$14:$B$8773,T10) -> 24519.302 | W10: =V10/U10 -> 0.98868154 | X10: =MAX(0,Assumptions!$C$24*U10-V10) -> 0 | Y10: =(V10+X10)/U10 -> 0.98868154 | Z10: =IF(Y10>=Assumptions!$C$24-0.000001,"PASS","FAIL") -> PASS
T11: 6 | U11: =SUMIFS($G$14:$G$8773,$B$14:$B$8773,T11) -> 24000 | V11: =SUMIFS($J$14:$J$8773,$B$14:$B$8773,T11) -> 23760.596 | W11: =V11/U11 -> 0.99002484 | X11: =MAX(0,Assumptions!$C$24*U11-V11) -> 0 | Y11: =(V11+X11)/U11 -> 0.99002484 | Z11: =IF(Y11>=Assumptions!$C$24-0.000001,"PASS","FAIL") -> PASS
T12: 7 | U12: =SUMIFS($G$14:$G$8773,$B$14:$B$8773,T12) -> 24800 | V12: =SUMIFS($J$14:$J$8773,$B$14:$B$8773,T12) -> 24603.102 | W12: =V12/U12 -> 0.99206058 | X12: =MAX(0,Assumptions!$C$24*U12-V12) -> 0 | Y12: =(V12+X12)/U12 -> 0.99206058 | Z12: =IF(Y12>=Assumptions!$C$24-0.000001,"PASS","FAIL") -> PASS
A13: Hour | B13: Month | C13: Peak | D13: SolarCF | E13: WindCF | F13: RE MW | G13: Peak target | H13: RE→peak | I13: BESS discharge | J13: Peak delivered | K13: BESS charge | L13: Non-peak PPA | M13: Rem peak obl | N13: PPA total | O13: Cum PPA | P13: SOC | Q13: Surplus | T13: 8 | U13: =SUMIFS($G$14:$G$8773,$B$14:$B$8773,T13) -> 24800 | V13: =SUMIFS($J$14:$J$8773,$B$14:$B$8773,T13) -> 24672.478 | W13: =V13/U13 -> 0.99485799 | X13: =MAX(0,Assumptions!$C$24*U13-V13) -> 0 | Y13: =(V13+X13)/U13 -> 0.99485799 | Z13: =IF(Y13>=Assumptions!$C$24-0.000001,"PASS","FAIL") -> PASS
A14: ='Profiles 8760'!A3 -> 1 | B14: ='Profiles 8760'!B3 -> 1 | C14: ='Profiles 8760'!E3 -> 0 | D14: ='Profiles 8760'!F3 -> 0 | E14: ='Profiles 8760'!G3 -> 0.209117 | F14: =D14*Assumptions!$C$11*$B$7+E14*Assumptions!$C$12*$B$8 -> 8.5528853 | G14: =C14*Assumptions!$C$15 -> 0 | H14: =MIN(F14,G14) -> 0 | I14: =IF(C14=1,MIN(G14-H14,Assumptions!$C$13,$B$9),0) -> 0 | J14: =H14+I14 -> 0 | K14: =MIN(IF(C14=1,F14-H14,F14),Assumptions!$C$13,MAX(0,($B$5-$B$9)/$B$6)) -> 8.5528853 | L14: =IF(C14=1,0,MIN(F14-K14,Assumptions!$C$15,MAX(0,$B$10-0-M14))) -> 0 | M14: ='Profiles 8760'!H3 -> 292000 | N14: =J14+L14 -> 0 | O14: =0+N14 -> 0 | P14: =MIN($B$5,$B$9+K14*$B$6-I14) -> 262.81864 | Q14: =MAX(0,F14-H14-K14-L14) -> 0 | T14: 9 | U14: =SUMIFS($G$14:$G$8773,$B$14:$B$8773,T14) -> 24000 | V14: =SUMIFS($J$14:$J$8773,$B$14:$B$8773,T14) -> 23700.355 | W14: =V14/U14 -> 0.9875148 | X14: =MAX(0,Assumptions!$C$24*U14-V14) -> 0 | Y14: =(V14+X14)/U14 -> 0.9875148 | Z14: =IF(Y14>=Assumptions!$C$24-0.000001,"PASS","FAIL") -> PASS
A15: ='Profiles 8760'!A4 -> 2 | B15: ='Profiles 8760'!B4 -> 1 | C15: ='Profiles 8760'!E4 -> 0 | D15: ='Profiles 8760'!F4 -> 0 | E15: ='Profiles 8760'!G4 -> 0.257582 | F15: =D15*Assumptions!$C$11*$B$7+E15*Assumptions!$C$12*$B$8 -> 10.535104 | G15: =C15*Assumptions!$C$15 -> 0 | H15: =MIN(F15,G15) -> 0 | I15: =IF(C15=1,MIN(G15-H15,Assumptions!$C$13,P14),0) -> 0 | J15: =H15+I15 -> 0 | K15: =MIN(IF(C15=1,F15-H15,F15),Assumptions!$C$13,MAX(0,($B$5-P14)/$B$6)) -> 10.535104 | L15: =IF(C15=1,0,MIN(F15-K15,Assumptions!$C$15,MAX(0,$B$10-O14-M15))) -> 0 | M15: ='Profiles 8760'!H4 -> 292000 | N15: =J15+L15 -> 0 | O15: =O14+N15 -> 0 | P15: =MIN($B$5,P14+K15*$B$6-I15) -> 271.95047 | Q15: =MAX(0,F15-H15-K15-L15) -> 0 | T15: 10 | U15: =SUMIFS($G$14:$G$8773,$B$14:$B$8773,T15) -> 24800 | V15: =SUMIFS($J$14:$J$8773,$B$14:$B$8773,T15) -> 24348.724 | W15: =V15/U15 -> 0.98180338 | X15: =MAX(0,Assumptions!$C$24*U15-V15) -> 0 | Y15: =(V15+X15)/U15 -> 0.98180338 | Z15: =IF(Y15>=Assumptions!$C$24-0.000001,"PASS","FAIL") -> PASS
A16: ='Profiles 8760'!A5 -> 3 | B16: ='Profiles 8760'!B5 -> 1 | C16: ='Profiles 8760'!E5 -> 0 | D16: ='Profiles 8760'!F5 -> 0 | E16: ='Profiles 8760'!G5 -> 0.274103 | F16: =D16*Assumptions!$C$11*$B$7+E16*Assumptions!$C$12*$B$8 -> 11.210813 | G16: =C16*Assumptions!$C$15 -> 0 | H16: =MIN(F16,G16) -> 0 | I16: =IF(C16=1,MIN(G16-H16,Assumptions!$C$13,P15),0) -> 0 | J16: =H16+I16 -> 0 | K16: =MIN(IF(C16=1,F16-H16,F16),Assumptions!$C$13,MAX(0,($B$5-P15)/$B$6)) -> 11.210813 | L16: =IF(C16=1,0,MIN(F16-K16,Assumptions!$C$15,MAX(0,$B$10-O15-M16))) -> 0 | M16: ='Profiles 8760'!H5 -> 292000 | N16: =J16+L16 -> 0 | O16: =O15+N16 -> 0 | P16: =MIN($B$5,P15+K16*$B$6-I16) -> 281.668 | Q16: =MAX(0,F16-H16-K16-L16) -> 0 | T16: 11 | U16: =SUMIFS($G$14:$G$8773,$B$14:$B$8773,T16) -> 24000 | V16: =SUMIFS($J$14:$J$8773,$B$14:$B$8773,T16) -> 22914.515 | W16: =V16/U16 -> 0.95477147 | X16: =MAX(0,Assumptions!$C$24*U16-V16) -> 0 | Y16: =(V16+X16)/U16 -> 0.95477147 | Z16: =IF(Y16>=Assumptions!$C$24-0.000001,"PASS","FAIL") -> PASS
A17: ='Profiles 8760'!A6 -> 4 | B17: ='Profiles 8760'!B6 -> 1 | C17: ='Profiles 8760'!E6 -> 0 | D17: ='Profiles 8760'!F6 -> 0 | E17: ='Profiles 8760'!G6 -> 0.368831 | F17: =D17*Assumptions!$C$11*$B$7+E17*Assumptions!$C$12*$B$8 -> 15.085188 | G17: =C17*Assumptions!$C$15 -> 0 | H17: =MIN(F17,G17) -> 0 | I17: =IF(C17=1,MIN(G17-H17,Assumptions!$C$13,P16),0) -> 0 | J17: =H17+I17 -> 0 | K17: =MIN(IF(C17=1,F17-H17,F17),Assumptions!$C$13,MAX(0,($B$5-P16)/$B$6)) -> 15.085188 | L17: =IF(C17=1,0,MIN(F17-K17,Assumptions!$C$15,MAX(0,$B$10-O16-M17))) -> 0 | M17: ='Profiles 8760'!H6 -> 292000 | N17: =J17+L17 -> 0 | O17: =O16+N17 -> 0 | P17: =MIN($B$5,P16+K17*$B$6-I17) -> 294.74384 | Q17: =MAX(0,F17-H17-K17-L17) -> 0 | T17: 12 | U17: =SUMIFS($G$14:$G$8773,$B$14:$B$8773,T17) -> 24800 | V17: =SUMIFS($J$14:$J$8773,$B$14:$B$8773,T17) -> 23046.03 | W17: =V17/U17 -> 0.92927539 | X17: =MAX(0,Assumptions!$C$24*U17-V17) -> 0 | Y17: =(V17+X17)/U17 -> 0.92927539 | Z17: =IF(Y17>=Assumptions!$C$24-0.000001,"PASS","FAIL") -> PASS
A18: ='Profiles 8760'!A7 -> 5 | B18: ='Profiles 8760'!B7 -> 1 | C18: ='Profiles 8760'!E7 -> 0 | D18: ='Profiles 8760'!F7 -> 0 | E18: ='Profiles 8760'!G7 -> 0.292277 | F18: =D18*Assumptions!$C$11*$B$7+E18*Assumptions!$C$12*$B$8 -> 11.954129 | G18: =C18*Assumptions!$C$15 -> 0 | H18: =MIN(F18,G18) -> 0 | I18: =IF(C18=1,MIN(G18-H18,Assumptions!$C$13,P17),0) -> 0 | J18: =H18+I18 -> 0 | K18: =MIN(IF(C18=1,F18-H18,F18),Assumptions!$C$13,MAX(0,($B$5-P17)/$B$6)) -> 11.954129 | L18: =IF(C18=1,0,MIN(F18-K18,Assumptions!$C$15,MAX(0,$B$10-O17-M18))) -> 0 | M18: ='Profiles 8760'!H7 -> 292000 | N18: =J18+L18 -> 0 | O18: =O17+N18 -> 0 | P18: =MIN($B$5,P17+K18*$B$6-I18) -> 305.10568 | Q18: =MAX(0,F18-H18-K18-L18) -> 0 | T18: YEAR | U18: =SUM(U6:U17) -> 292000 | V18: =SUM(V6:V17) -> 283836.11 | W18: =MIN(W6:W17) -> 0.9201293 | X18: =SUM(X6:X17) -> 0 | Z18: =IF(COUNTIF(Z6:Z17,"FAIL")=0,"ALL PASS","FAIL") -> ALL PASS
A19: ='Profiles 8760'!A8 -> 6 | B19: ='Profiles 8760'!B8 -> 1 | C19: ='Profiles 8760'!E8 -> 0 | D19: ='Profiles 8760'!F8 -> 0 | E19: ='Profiles 8760'!G8 -> 0.193604 | F19: =D19*Assumptions!$C$11*$B$7+E19*Assumptions!$C$12*$B$8 -> 7.9184036 | G19: =C19*Assumptions!$C$15 -> 0 | H19: =MIN(F19,G19) -> 0 | I19: =IF(C19=1,MIN(G19-H19,Assumptions!$C$13,P18),0) -> 0 | J19: =H19+I19 -> 0 | K19: =MIN(IF(C19=1,F19-H19,F19),Assumptions!$C$13,MAX(0,($B$5-P18)/$B$6)) -> 7.9184036 | L19: =IF(C19=1,0,MIN(F19-K19,Assumptions!$C$15,MAX(0,$B$10-O18-M19))) -> 0 | M19: ='Profiles 8760'!H8 -> 292000 | N19: =J19+L19 -> 0 | O19: =O18+N19 -> 0 | P19: =MIN($B$5,P18+K19*$B$6-I19) -> 311.96935 | Q19: =MAX(0,F19-H19-K19-L19) -> 0
A20: ='Profiles 8760'!A9 -> 7 | B20: ='Profiles 8760'!B9 -> 1 | C20: ='Profiles 8760'!E9 -> 0 | D20: ='Profiles 8760'!F9 -> 0 | E20: ='Profiles 8760'!G9 -> 0.157591 | F20: =D20*Assumptions!$C$11*$B$7+E20*Assumptions!$C$12*$B$8 -> 6.4454719 | G20: =C20*Assumptions!$C$15 -> 0 | H20: =MIN(F20,G20) -> 0 | I20: =IF(C20=1,MIN(G20-H20,Assumptions!$C$13,P19),0) -> 0 | J20: =H20+I20 -> 0 | K20: =MIN(IF(C20=1,F20-H20,F20),Assumptions!$C$13,MAX(0,($B$5-P19)/$B$6)) -> 6.4454719 | L20: =IF(C20=1,0,MIN(F20-K20,Assumptions!$C$15,MAX(0,$B$10-O19-M20))) -> 0 | M20: ='Profiles 8760'!H9 -> 292000 | N20: =J20+L20 -> 0 | O20: =O19+N20 -> 0 | P20: =MIN($B$5,P19+K20*$B$6-I20) -> 317.55629 | Q20: =MAX(0,F20-H20-K20-L20) -> 0
A21: ='Profiles 8760'!A10 -> 8 | B21: ='Profiles 8760'!B10 -> 1 | C21: ='Profiles 8760'!E10 -> 1 | D21: ='Profiles 8760'!F10 -> 0.06852 | E21: ='Profiles 8760'!G10 -> 0.20751 | F21: =D21*Assumptions!$C$11*$B$7+E21*Assumptions!$C$12*$B$8 -> 28.275735 | G21: =C21*Assumptions!$C$15 -> 200 | H21: =MIN(F21,G21) -> 28.275735 | I21: =IF(C21=1,MIN(G21-H21,Assumptions!$C$13,P20),0) -> 171.72427 | J21: =H21+I21 -> 200 | K21: =MIN(IF(C21=1,F21-H21,F21),Assumptions!$C$13,MAX(0,($B$5-P20)/$B$6)) -> 0 | L21: =IF(C21=1,0,MIN(F21-K21,Assumptions!$C$15,MAX(0,$B$10-O20-M21))) -> 0 | M21: ='Profiles 8760'!H10 -> 291800 | N21: =J21+L21 -> 200 | O21: =O20+N21 -> 200 | P21: =MIN($B$5,P20+K21*$B$6-I21) -> 145.83202 | Q21: =MAX(0,F21-H21-K21-L21) -> 0 | T21: ANNUAL RESULT & ENGINE CROSS-CHECK
A22: ='Profiles 8760'!A11 -> 9 | B22: ='Profiles 8760'!B11 -> 1 | C22: ='Profiles 8760'!E11 -> 1 | D22: ='Profiles 8760'!F11 -> 0.359201 | E22: ='Profiles 8760'!G11 -> 0.347475 | F22: =D22*Assumptions!$C$11*$B$7+E22*Assumptions!$C$12*$B$8 -> 117.94898 | G22: =C22*Assumptions!$C$15 -> 200 | H22: =MIN(F22,G22) -> 117.94898 | I22: =IF(C22=1,MIN(G22-H22,Assumptions!$C$13,P21),0) -> 82.051024 | J22: =H22+I22 -> 200 | K22: =MIN(IF(C22=1,F22-H22,F22),Assumptions!$C$13,MAX(0,($B$5-P21)/$B$6)) -> 0 | L22: =IF(C22=1,0,MIN(F22-K22,Assumptions!$C$15,MAX(0,$B$10-O21-M22))) -> 0 | M22: ='Profiles 8760'!H11 -> 291600 | N22: =J22+L22 -> 200 | O22: =O21+N22 -> 400 | P22: =MIN($B$5,P21+K22*$B$6-I22) -> 63.781 | Q22: =MAX(0,F22-H22-K22-L22) -> 0 | T22: Metric | U22: This sheet | V22: Engine (exact) | W22: Delta %
A23: ='Profiles 8760'!A12 -> 10 | B23: ='Profiles 8760'!B12 -> 1 | C23: ='Profiles 8760'!E12 -> 0 | D23: ='Profiles 8760'!F12 -> 0.690594 | E23: ='Profiles 8760'!G12 -> 0.291436 | F23: =D23*Assumptions!$C$11*$B$7+E23*Assumptions!$C$12*$B$8 -> 211.36328 | G23: =C23*Assumptions!$C$15 -> 0 | H23: =MIN(F23,G23) -> 0 | I23: =IF(C23=1,MIN(G23-H23,Assumptions!$C$13,P22),0) -> 0 | J23: =H23+I23 -> 0 | K23: =MIN(IF(C23=1,F23-H23,F23),Assumptions!$C$13,MAX(0,($B$5-P22)/$B$6)) -> 180 | L23: =IF(C23=1,0,MIN(F23-K23,Assumptions!$C$15,MAX(0,$B$10-O22-M23))) -> 31.36328 | M23: ='Profiles 8760'!H12 -> 291600 | N23: =J23+L23 -> 31.36328 | O23: =O22+N23 -> 431.36328 | P23: =MIN($B$5,P22+K23*$B$6-I23) -> 219.805 | Q23: =MAX(0,F23-H23-K23-L23) -> 0 | T23: PPA energy MWh (project, before green) | U23: =SUM($N$14:$N$8773) -> 771406.67 | V23: =INDEX('25Y Hourly Validation'!G5:G29,$B$4) -> 771408 | W23: =IF(ABS(V23)>0.0001,(U23-V23)/ABS(V23),0) -> -1.7197309e-06
A24: ='Profiles 8760'!A13 -> 11 | B24: ='Profiles 8760'!B13 -> 1 | C24: ='Profiles 8760'!E13 -> 0 | D24: ='Profiles 8760'!F13 -> 0.983899 | E24: ='Profiles 8760'!G13 -> 0.305138 | F24: =D24*Assumptions!$C$11*$B$7+E24*Assumptions!$C$12*$B$8 -> 296.63018 | G24: =C24*Assumptions!$C$15 -> 0 | H24: =MIN(F24,G24) -> 0 | I24: =IF(C24=1,MIN(G24-H24,Assumptions!$C$13,P23),0) -> 0 | J24: =H24+I24 -> 0 | K24: =MIN(IF(C24=1,F24-H24,F24),Assumptions!$C$13,MAX(0,($B$5-P23)/$B$6)) -> 180 | L24: =IF(C24=1,0,MIN(F24-K24,Assumptions!$C$15,MAX(0,$B$10-O23-M24))) -> 116.63018 | M24: ='Profiles 8760'!H13 -> 291600 | N24: =J24+L24 -> 116.63018 | O24: =O23+N24 -> 547.99346 | P24: =MIN($B$5,P23+K24*$B$6-I24) -> 375.829 | Q24: =MAX(0,F24-H24-K24-L24) -> 0 | T24: Annual PPA CUF | U24: =U23/(Assumptions!$C$15*Assumptions!$C$23) -> 0.43999924 | V24: =INDEX('25Y Hourly Validation'!H5:H29,$B$4) -> 0.44 | W24: =IF(ABS(V24)>0.0001,(U24-V24)/ABS(V24),0) -> -1.7197309e-06
A25: ='Profiles 8760'!A14 -> 12 | B25: ='Profiles 8760'!B14 -> 1 | C25: ='Profiles 8760'!E14 -> 0 | D25: ='Profiles 8760'!F14 -> 1 | E25: ='Profiles 8760'!G14 -> 0.306961 | F25: =D25*Assumptions!$C$11*$B$7+E25*Assumptions!$C$12*$B$8 -> 301.3547 | G25: =C25*Assumptions!$C$15 -> 0 | H25: =MIN(F25,G25) -> 0 | I25: =IF(C25=1,MIN(G25-H25,Assumptions!$C$13,P24),0) -> 0 | J25: =H25+I25 -> 0 | K25: =MIN(IF(C25=1,F25-H25,F25),Assumptions!$C$13,MAX(0,($B$5-P24)/$B$6)) -> 155.72335 | L25: =IF(C25=1,0,MIN(F25-K25,Assumptions!$C$15,MAX(0,$B$10-O24-M25))) -> 145.63135 | M25: ='Profiles 8760'!H14 -> 291600 | N25: =J25+L25 -> 145.63135 | O25: =O24+N25 -> 693.62481 | P25: =MIN($B$5,P24+K25*$B$6-I25) -> 510.81 | Q25: =MAX(0,F25-H25-K25-L25) -> 0 | T25: Min monthly availability (delivered) | U25: =W18 -> 0.9201293 | V25: =INDEX('25Y Hourly Validation'!J5:J29,$B$4) -> 0.8241 | W25: =IF(ABS(V25)>0.0001,(U25-V25)/ABS(V25),0) -> 0.11652627
A26: ='Profiles 8760'!A15 -> 13 | B26: ='Profiles 8760'!B15 -> 1 | C26: ='Profiles 8760'!E15 -> 0 | D26: ='Profiles 8760'!F15 -> 1 | E26: ='Profiles 8760'!G15 -> 0.492777 | F26: =D26*Assumptions!$C$11*$B$7+E26*Assumptions!$C$12*$B$8 -> 308.95458 | G26: =C26*Assumptions!$C$15 -> 0 | H26: =MIN(F26,G26) -> 0 | I26: =IF(C26=1,MIN(G26-H26,Assumptions!$C$13,P25),0) -> 0 | J26: =H26+I26 -> 0 | K26: =MIN(IF(C26=1,F26-H26,F26),Assumptions!$C$13,MAX(0,($B$5-P25)/$B$6)) -> 0 | L26: =IF(C26=1,0,MIN(F26-K26,Assumptions!$C$15,MAX(0,$B$10-O25-M26))) -> 200 | M26: ='Profiles 8760'!H15 -> 291600 | N26: =J26+L26 -> 200 | O26: =O25+N26 -> 893.62481 | P26: =MIN($B$5,P25+K26*$B$6-I26) -> 510.81 | Q26: =MAX(0,F26-H26-K26-L26) -> 108.95458 | T26: Green support needed (MWh) | U26: =X18 -> 0 | V26: =INDEX('25Y Hourly Validation'!K5:K29,$B$4) -> 4556.8 | W26: =IF(ABS(V26)>0.0001,(U26-V26)/ABS(V26),0) -> -1
A27: ='Profiles 8760'!A16 -> 14 | B27: ='Profiles 8760'!B16 -> 1 | C27: ='Profiles 8760'!E16 -> 0 | D27: ='Profiles 8760'!F16 -> 1 | E27: ='Profiles 8760'!G16 -> 0.50808 | F27: =D27*Assumptions!$C$11*$B$7+E27*Assumptions!$C$12*$B$8 -> 309.58047 | G27: =C27*Assumptions!$C$15 -> 0 | H27: =MIN(F27,G27) -> 0 | I27: =IF(C27=1,MIN(G27-H27,Assumptions!$C$13,P26),0) -> 0 | J27: =H27+I27 -> 0 | K27: =MIN(IF(C27=1,F27-H27,F27),Assumptions!$C$13,MAX(0,($B$5-P26)/$B$6)) -> 0 | L27: =IF(C27=1,0,MIN(F27-K27,Assumptions!$C$15,MAX(0,$B$10-O26-M27))) -> 200 | M27: ='Profiles 8760'!H16 -> 291600 | N27: =J27+L27 -> 200 | O27: =O26+N27 -> 1093.6248 | P27: =MIN($B$5,P26+K27*$B$6-I27) -> 510.81 | Q27: =MAX(0,F27-H27-K27-L27) -> 109.58047
A28: ='Profiles 8760'!A17 -> 15 | B28: ='Profiles 8760'!B17 -> 1 | C28: ='Profiles 8760'!E17 -> 0 | D28: ='Profiles 8760'!F17 -> 0.983899 | E28: ='Profiles 8760'!G17 -> 0.487467 | F28: =D28*Assumptions!$C$11*$B$7+E28*Assumptions!$C$12*$B$8 -> 304.08743 | G28: =C28*Assumptions!$C$15 -> 0 | H28: =MIN(F28,G28) -> 0 | I28: =IF(C28=1,MIN(G28-H28,Assumptions!$C$13,P27),0) -> 0 | J28: =H28+I28 -> 0 | K28: =MIN(IF(C28=1,F28-H28,F28),Assumptions!$C$13,MAX(0,($B$5-P27)/$B$6)) -> 0 | L28: =IF(C28=1,0,MIN(F28-K28,Assumptions!$C$15,MAX(0,$B$10-O27-M28))) -> 200 | M28: ='Profiles 8760'!H17 -> 291600 | N28: =J28+L28 -> 200 | O28: =O27+N28 -> 1293.6248 | P28: =MIN($B$5,P27+K28*$B$6-I28) -> 510.81 | Q28: =MAX(0,F28-H28-K28-L28) -> 104.08743 | T28: CUF band check (this sheet) | U28: =IF(AND(U24>=Assumptions!$C$19*(1-Assumptions!$C$20),U24<=Assumptions!$C$19*Assumptions!$C$21+0.000001),"PASS","FAIL") -> PASS
A29: ='Profiles 8760'!A18 -> 16 | B29: ='Profiles 8760'!B18 -> 1 | C29: ='Profiles 8760'!E18 -> 0 | D29: ='Profiles 8760'!F18 -> 0.690594 | E29: ='Profiles 8760'!G18 -> 0.420836 | F29: =D29*Assumptions!$C$11*$B$7+E29*Assumptions!$C$12*$B$8 -> 216.65574 | G29: =C29*Assumptions!$C$15 -> 0 | H29: =MIN(F29,G29) -> 0 | I29: =IF(C29=1,MIN(G29-H29,Assumptions!$C$13,P28),0) -> 0 | J29: =H29+I29 -> 0 | K29: =MIN(IF(C29=1,F29-H29,F29),Assumptions!$C$13,MAX(0,($B$5-P28)/$B$6)) -> 0 | L29: =IF(C29=1,0,MIN(F29-K29,Assumptions!$C$15,MAX(0,$B$10-O28-M29))) -> 200 | M29: ='Profiles 8760'!H18 -> 291600 | N29: =J29+L29 -> 200 | O29: =O28+N29 -> 1493.6248 | P29: =MIN($B$5,P28+K29*$B$6-I29) -> 510.81 | Q29: =MAX(0,F29-H29-K29-L29) -> 16.65574 | T29: Deltas vs engine arise from single-node aggregation (engine enforces per-node interconnection limits, e.g. 30 MW at Fatehgarh wind).
A30: ='Profiles 8760'!A19 -> 17 | B30: ='Profiles 8760'!B19 -> 1 | C30: ='Profiles 8760'!E19 -> 0 | D30: ='Profiles 8760'!F19 -> 0.359201 | E30: ='Profiles 8760'!G19 -> 0.497041 | F30: =D30*Assumptions!$C$11*$B$7+E30*Assumptions!$C$12*$B$8 -> 124.06623 | G30: =C30*Assumptions!$C$15 -> 0 | H30: =MIN(F30,G30) -> 0 | I30: =IF(C30=1,MIN(G30-H30,Assumptions!$C$13,P29),0) -> 0 | J30: =H30+I30 -> 0 | K30: =MIN(IF(C30=1,F30-H30,F30),Assumptions!$C$13,MAX(0,($B$5-P29)/$B$6)) -> 0 | L30: =IF(C30=1,0,MIN(F30-K30,Assumptions!$C$15,MAX(0,$B$10-O29-M30))) -> 124.06623 | M30: ='Profiles 8760'!H19 -> 291600 | N30: =J30+L30 -> 124.06623 | O30: =O29+N30 -> 1617.691 | P30: =MIN($B$5,P29+K30*$B$6-I30) -> 510.81 | Q30: =MAX(0,F30-H30-K30-L30) -> 0
A31: ='Profiles 8760'!A20 -> 18 | B31: ='Profiles 8760'!B20 -> 1 | C31: ='Profiles 8760'!E20 -> 0 | D31: ='Profiles 8760'!F20 -> 0.06852 | E31: ='Profiles 8760'!G20 -> 0.332405 | F31: =D31*Assumptions!$C$11*$B$7+E31*Assumptions!$C$12*$B$8 -> 33.383941 | G31: =C31*Assumptions!$C$15 -> 0 | H31: =MIN(F31,G31) -> 0 | I31: =IF(C31=1,MIN(G31-H31,Assumptions!$C$13,P30),0) -> 0 | J31: =H31+I31 -> 0 | K31: =MIN(IF(C31=1,F31-H31,F31),Assumptions!$C$13,MAX(0,($B$5-P30)/$B$6)) -> 0 | L31: =IF(C31=1,0,MIN(F31-K31,Assumptions!$C$15,MAX(0,$B$10-O30-M31))) -> 33.383941 | M31: ='Profiles 8760'!H20 -> 291600 | N31: =J31+L31 -> 33.383941 | O31: =O30+N31 -> 1651.075 | P31: =MIN($B$5,P30+K31*$B$6-I31) -> 510.81 | Q31: =MAX(0,F31-H31-K31-L31) -> 0
A32: ='Profiles 8760'!A21 -> 19 | B32: ='Profiles 8760'!B21 -> 1 | C32: ='Profiles 8760'!E21 -> 0 | D32: ='Profiles 8760'!F21 -> 0 | E32: ='Profiles 8760'!G21 -> 0.253196 | F32: =D32*Assumptions!$C$11*$B$7+E32*Assumptions!$C$12*$B$8 -> 10.355716 | G32: =C32*Assumptions!$C$15 -> 0 | H32: =MIN(F32,G32) -> 0 | I32: =IF(C32=1,MIN(G32-H32,Assumptions!$C$13,P31),0) -> 0 | J32: =H32+I32 -> 0 | K32: =MIN(IF(C32=1,F32-H32,F32),Assumptions!$C$13,MAX(0,($B$5-P31)/$B$6)) -> 0 | L32: =IF(C32=1,0,MIN(F32-K32,Assumptions!$C$15,MAX(0,$B$10-O31-M32))) -> 10.355716 | M32: ='Profiles 8760'!H21 -> 291600 | N32: =J32+L32 -> 10.355716 | O32: =O31+N32 -> 1661.4307 | P32: =MIN($B$5,P31+K32*$B$6-I32) -> 510.81 | Q32: =MAX(0,F32-H32-K32-L32) -> 0
A33: ='Profiles 8760'!A22 -> 20 | B33: ='Profiles 8760'!B22 -> 1 | C33: ='Profiles 8760'!E22 -> 1 | D33: ='Profiles 8760'!F22 -> 0 | E33: ='Profiles 8760'!G22 -> 0.319058 | F33: =D33*Assumptions!$C$11*$B$7+E33*Assumptions!$C$12*$B$8 -> 13.049472 | G33: =C33*Assumptions!$C$15 -> 200 | H33: =MIN(F33,G33) -> 13.049472 | I33: =IF(C33=1,MIN(G33-H33,Assumptions!$C$13,P32),0) -> 180 | J33: =H33+I33 -> 193.04947 | K33: =MIN(IF(C33=1,F33-H33,F33),Assumptions!$C$13,MAX(0,($B$5-P32)/$B$6)) -> 0 | L33: =IF(C33=1,0,MIN(F33-K33,Assumptions!$C$15,MAX(0,$B$10-O32-M33))) -> 0 | M33: ='Profiles 8760'!H22 -> 291400 | N33: =J33+L33 -> 193.04947 | O33: =O32+N33 -> 1854.4802 | P33: =MIN($B$5,P32+K33*$B$6-I33) -> 330.81 | Q33: =MAX(0,F33-H33-K33-L33) -> 0
A34: ='Profiles 8760'!A23 -> 21 | B34: ='Profiles 8760'!B23 -> 1 | C34: ='Profiles 8760'!E23 -> 1 | D34: ='Profiles 8760'!F23 -> 0 | E34: ='Profiles 8760'!G23 -> 0.201444 | F34: =D34*Assumptions!$C$11*$B$7+E34*Assumptions!$C$12*$B$8 -> 8.2390596 | G34: =C34*Assumptions!$C$15 -> 200 | H34: =MIN(F34,G34) -> 8.2390596 | I34: =IF(C34=1,MIN(G34-H34,Assumptions!$C$13,P33),0) -> 180 | J34: =H34+I34 -> 188.23906 | K34: =MIN(IF(C34=1,F34-H34,F34),Assumptions!$C$13,MAX(0,($B$5-P33)/$B$6)) -> 0 | L34: =IF(C34=1,0,MIN(F34-K34,Assumptions!$C$15,MAX(0,$B$10-O33-M34))) -> 0 | M34: ='Profiles 8760'!H23 -> 291200 | N34: =J34+L34 -> 188.23906 | O34: =O33+N34 -> 2042.7192 | P34: =MIN($B$5,P33+K34*$B$6-I34) -> 150.81 | Q34: =MAX(0,F34-H34-K34-L34) -> 0
A35: ='Profiles 8760'!A24 -> 22 | B35: ='Profiles 8760'!B24 -> 1 | C35: ='Profiles 8760'!E24 -> 0 | D35: ='Profiles 8760'!F24 -> 0 | E35: ='Profiles 8760'!G24 -> 0.162566 | F35: =D35*Assumptions!$C$11*$B$7+E35*Assumptions!$C$12*$B$8 -> 6.6489494 | G35: =C35*Assumptions!$C$15 -> 0 | H35: =MIN(F35,G35) -> 0 | I35: =IF(C35=1,MIN(G35-H35,Assumptions!$C$13,P34),0) -> 0 | J35: =H35+I35 -> 0 | K35: =MIN(IF(C35=1,F35-H35,F35),Assumptions!$C$13,MAX(0,($B$5-P34)/$B$6)) -> 6.6489494 | L35: =IF(C35=1,0,MIN(F35-K35,Assumptions!$C$15,MAX(0,$B$10-O34-M35))) -> 0 | M35: ='Profiles 8760'!H24 -> 291200 | N35: =J35+L35 -> 0 | O35: =O34+N35 -> 2042.7192 | P35: =MIN($B$5,P34+K35*$B$6-I35) -> 156.57331 | Q35: =MAX(0,F35-H35-K35-L35) -> 0
A36: ='Profiles 8760'!A25 -> 23 | B36: ='Profiles 8760'!B25 -> 1 | C36: ='Profiles 8760'!E25 -> 0 | D36: ='Profiles 8760'!F25 -> 0 | E36: ='Profiles 8760'!G25 -> 0.092644 | F36: =D36*Assumptions!$C$11*$B$7+E36*Assumptions!$C$12*$B$8 -> 3.7891396 | G36: =C36*Assumptions!$C$15 -> 0 | H36: =MIN(F36,G36) -> 0 | I36: =IF(C36=1,MIN(G36-H36,Assumptions!$C$13,P35),0) -> 0 | J36: =H36+I36 -> 0 | K36: =MIN(IF(C36=1,F36-H36,F36),Assumptions!$C$13,MAX(0,($B$5-P35)/$B$6)) -> 3.7891396 | L36: =IF(C36=1,0,MIN(F36-K36,Assumptions!$C$15,MAX(0,$B$10-O35-M36))) -> 0 | M36: ='Profiles 8760'!H25 -> 291200 | N36: =J36+L36 -> 0 | O36: =O35+N36 -> 2042.7192 | P36: =MIN($B$5,P35+K36*$B$6-I36) -> 159.85774 | Q36: =MAX(0,F36-H36-K36-L36) -> 0
A37: ='Profiles 8760'!A26 -> 24 | B37: ='Profiles 8760'!B26 -> 1 | C37: ='Profiles 8760'!E26 -> 0 | D37: ='Profiles 8760'!F26 -> 0 | E37: ='Profiles 8760'!G26 -> 0.063263 | F37: =D37*Assumptions!$C$11*$B$7+E37*Assumptions!$C$12*$B$8 -> 2.5874567 | G37: =C37*Assumptions!$C$15 -> 0 | H37: =MIN(F37,G37) -> 0 | I37: =IF(C37=1,MIN(G37-H37,Assumptions!$C$13,P36),0) -> 0 | J37: =H37+I37 -> 0 | K37: =MIN(IF(C37=1,F37-H37,F37),Assumptions!$C$13,MAX(0,($B$5-P36)/$B$6)) -> 2.5874567 | L37: =IF(C37=1,0,MIN(F37-K37,Assumptions!$C$15,MAX(0,$B$10-O36-M37))) -> 0 | M37: ='Profiles 8760'!H26 -> 291200 | N37: =J37+L37 -> 0 | O37: =O36+N37 -> 2042.7192 | P37: =MIN($B$5,P36+K37*$B$6-I37) -> 162.10054 | Q37: =MAX(0,F37-H37-K37-L37) -> 0
A38: ='Profiles 8760'!A27 -> 25 | B38: ='Profiles 8760'!B27 -> 1 | C38: ='Profiles 8760'!E27 -> 0 | D38: ='Profiles 8760'!F27 -> 0 | E38: ='Profiles 8760'!G27 -> 0.073818 | F38: =D38*Assumptions!$C$11*$B$7+E38*Assumptions!$C$12*$B$8 -> 3.0191562 | G38: =C38*Assumptions!$C$15 -> 0 | H38: =MIN(F38,G38) -> 0 | I38: =IF(C38=1,MIN(G38-H38,Assumptions!$C$13,P37),0) -> 0 | J38: =H38+I38 -> 0 | K38: =MIN(IF(C38=1,F38-H38,F38),Assumptions!$C$13,MAX(0,($B$5-P37)/$B$6)) -> 3.0191562 | L38: =IF(C38=1,0,MIN(F38-K38,Assumptions!$C$15,MAX(0,$B$10-O37-M38))) -> 0 | M38: ='Profiles 8760'!H27 -> 291200 | N38: =J38+L38 -> 0 | O38: =O37+N38 -> 2042.7192 | P38: =MIN($B$5,P37+K38*$B$6-I38) -> 164.71755 | Q38: =MAX(0,F38-H38-K38-L38) -> 0
A39: ='Profiles 8760'!A28 -> 26 | B39: ='Profiles 8760'!B28 -> 1 | C39: ='Profiles 8760'!E28 -> 0 | D39: ='Profiles 8760'!F28 -> 0 | E39: ='Profiles 8760'!G28 -> 0.059784 | F39: =D39*Assumptions!$C$11*$B$7+E39*Assumptions!$C$12*$B$8 -> 2.4451656 | G39: =C39*Assumptions!$C$15 -> 0 | H39: =MIN(F39,G39) -> 0 | I39: =IF(C39=1,MIN(G39-H39,Assumptions!$C$13,P38),0) -> 0 | J39: =H39+I39 -> 0 | K39: =MIN(IF(C39=1,F39-H39,F39),Assumptions!$C$13,MAX(0,($B$5-P38)/$B$6)) -> 2.4451656 | L39: =IF(C39=1,0,MIN(F39-K39,Assumptions!$C$15,MAX(0,$B$10-O38-M39))) -> 0 | M39: ='Profiles 8760'!H28 -> 291200 | N39: =J39+L39 -> 0 | O39: =O38+N39 -> 2042.7192 | P39: =MIN($B$5,P38+K39*$B$6-I39) -> 166.83702 | Q39: =MAX(0,F39-H39-K39-L39) -> 0
A40: ='Profiles 8760'!A29 -> 27 | B40: ='Profiles 8760'!B29 -> 1 | C40: ='Profiles 8760'!E29 -> 0 | D40: ='Profiles 8760'!F29 -> 0 | E40: ='Profiles 8760'!G29 -> 0.052314 | F40: =D40*Assumptions!$C$11*$B$7+E40*Assumptions!$C$12*$B$8 -> 2.1396426 | G40: =C40*Assumptions!$C$15 -> 0 | H40: =MIN(F40,G40) -> 0 | I40: =IF(C40=1,MIN(G40-H40,Assumptions!$C$13,P39),0) -> 0 | J40: =H40+I40 -> 0 | K40: =MIN(IF(C40=1,F40-H40,F40),Assumptions!$C$13,MAX(0,($B$5-P39)/$B$6)) -> 2.1396426 | L40: =IF(C40=1,0,MIN(F40-K40,Assumptions!$C$15,MAX(0,$B$10-O39-M40))) -> 0 | M40: ='Profiles 8760'!H29 -> 291200 | N40: =J40+L40 -> 0 | O40: =O39+N40 -> 2042.7192 | P40: =MIN($B$5,P39+K40*$B$6-I40) -> 168.69166 | Q40: =MAX(0,F40-H40-K40-L40) -> 0
A41: ='Profiles 8760'!A30 -> 28 | B41: ='Profiles 8760'!B30 -> 1 | C41: ='Profiles 8760'!E30 -> 0 | D41: ='Profiles 8760'!F30 -> 0 | E41: ='Profiles 8760'!G30 -> 0.053166 | F41: =D41*Assumptions!$C$11*$B$7+E41*Assumptions!$C$12*$B$8 -> 2.1744894 | G41: =C41*Assumptions!$C$15 -> 0 | H41: =MIN(F41,G41) -> 0 | I41: =IF(C41=1,MIN(G41-H41,Assumptions!$C$13,P40),0) -> 0 | J41: =H41+I41 -> 0 | K41: =MIN(IF(C41=1,F41-H41,F41),Assumptions!$C$13,MAX(0,($B$5-P40)/$B$6)) -> 2.1744894 | L41: =IF(C41=1,0,MIN(F41-K41,Assumptions!$C$15,MAX(0,$B$10-O40-M41))) -> 0 | M41: ='Profiles 8760'!H30 -> 291200 | N41: =J41+L41 -> 0 | O41: =O40+N41 -> 2042.7192 | P41: =MIN($B$5,P40+K41*$B$6-I41) -> 170.57651 | Q41: =MAX(0,F41-H41-K41-L41) -> 0
... A8773: ='Profiles 8760'!A8762 -> 8760 | B8773: ='Profiles 8760'!B8762 -> 12 | C8773: ='Profiles 8760'!E8762 -> 0 | D8773: ='Profiles 8760'!F8762 -> 0 | E8773: ='Profiles 8760'!G8762 -> 0.857641 | F8773: =D8773*Assumptions!$C$11*$B$7+E8773*Assumptions!$C$12*$B$8 -> 35.077517 | G8773: =C8773*Assumptions!$C$15 -> 0 | H8773: =MIN(F8773,G8773) -> 0 | I8773: =IF(C8773=1,MIN(G8773-H8773,Assumptions!$C$13,P8772),0) -> 0 | J8773: =H8773+I8773 -> 0 | K8773: =MIN(IF(C8773=1,F8773-H8773,F8773),Assumptions!$C$13,MAX(0,($B$5-P8772)/$B$6)) -> 35.077517 | L8773: =IF(C8773=1,0,MIN(F8773-K8773,Assumptions!$C$15,MAX(0,$B$10-O8772-M8773))) -> 0 | M8773: ='Profiles 8760'!H8762 -> 0 | N8773: =J8773+L8773 -> 0 | O8773: =O8772+N8773 -> 771406.67 | P8773: =MIN($B$5,P8772+K8773*$B$6-I8773) -> 249.02852 | Q8773: =MAX(0,F8773-H8773-K8773-L8773) -> 0
